{
  "updatedAt": "2026-06-28",
  "season": 2026,
  "predictions": [
    {
      "pid": 656941,
      "name": "",
      "team": "PHI",
      "gameProb": 0.1153,
      "gameMatchup": "PHI @ NYM",
      "battingOrder": 2,
      "pitcherName": "Cionel P\u00e9rez",
      "grade": "C",
      "factors": {
        "iso": 1.0,
        "platoon": 1.15,
        "park": 1.0,
        "wind": 1.0,
        "temp": 0.93,
        "kTrend": 1.0,
        "bullpen": 1.0,
        "pitFatigue": 1.0,
        "convergence": 1.06
      }
    },
    {
      "pid": 696100,
      "name": "",
      "team": "COL",
      "gameProb": 0.1097,
      "gameMatchup": "COL @ MIN",
      "battingOrder": 3,
      "pitcherName": "Connor Prielipp",
      "grade": "C",
      "factors": {
        "iso": 1.0,
        "platoon": 1.15,
        "park": 1.0,
        "wind": 1.0,
        "temp": 0.93,
        "kTrend": 1.0,
        "bullpen": 1.0,
        "pitFatigue": 1.0,
        "convergence": 1.06
      }
    },
    {
      "pid": 665742,
      "name": "",
      "team": "NYM",
      "gameProb": 0.0926,
      "gameMatchup": "NYM vs PHI",
      "battingOrder": 2,
      "pitcherName": "Jes\u00fas Luzardo",
      "grade": "C",
      "factors": {
        "iso": 1.0,
        "platoon": 1.15,
        "park": 1.0,
        "wind": 1.0,
        "temp": 0.93,
        "kTrend": 1.0,
        "bullpen": 1.0,
        "pitFatigue": 1.0,
        "convergence": 1.06
      }
    },
    {
      "pid": 547180,
      "name": "",
      "team": "PHI",
      "gameProb": 0.084,
      "gameMatchup": "PHI @ NYM",
      "battingOrder": 3,
      "pitcherName": "Cionel P\u00e9rez",
      "grade": "C",
      "factors": {
        "iso": 1.0,
        "platoon": 1.15,
        "park": 1.0,
        "wind": 1.0,
        "temp": 0.93,
        "kTrend": 1.0,
        "bullpen": 1.0,
        "pitFatigue": 1.0,
        "convergence": 1.06
      }
    },
    {
      "pid": 694192,
      "name": "",
      "team": "MIL",
      "gameProb": 0.0779,
      "gameMatchup": "MIL vs CHC",
      "battingOrder": 2,
      "pitcherName": "Ryan Rolison",
      "grade": "D",
      "factors": {
        "iso": 1.0,
        "platoon": 1.15,
        "park": 1.0,
        "wind": 1.0,
        "temp": 0.93,
        "kTrend": 1.0,
        "bullpen": 1.0,
        "pitFatigue": 1.0,
        "convergence": 1.06
      }
    },
    {
      "pid": 621439,
      "name": "",
      "team": "MIN",
      "gameProb": 0.0759,
      "gameMatchup": "MIN vs COL",
      "battingOrder": 2,
      "pitcherName": "Ryan Feltner",
      "grade": "D",
      "factors": {
        "iso": 1.0,
        "platoon": 0.96,
        "park": 1.0,
        "wind": 1.0,
        "temp": 0.93,
        "kTrend": 1.0,
        "bullpen": 1.0,
        "pitFatigue": 1.0,
        "convergence": 1.03
      }
    },
    {
      "pid": 641343,
      "name": "",
      "team": "MIL",
      "gameProb": 0.0732,
      "gameMatchup": "MIL vs CHC",
      "battingOrder": 5,
      "pitcherName": "Ryan Rolison",
      "grade": "D",
      "factors": {
        "iso": 1.0,
        "platoon": 1.15,
        "park": 1.0,
        "wind": 1.0,
        "temp": 0.93,
        "kTrend": 1.0,
        "bullpen": 1.0,
        "pitFatigue": 1.0,
        "convergence": 1.06
      }
    },
    {
      "pid": 670541,
      "name": "",
      "team": "HOU",
      "gameProb": 0.0717,
      "gameMatchup": "HOU @ DET",
      "battingOrder": 2,
      "pitcherName": "Jack Flaherty",
      "grade": "D",
      "factors": {
        "iso": 1.0,
        "platoon": 0.96,
        "park": 1.02,
        "wind": 1.0,
        "temp": 0.93,
        "kTrend": 1.0,
        "bullpen": 1.0,
        "pitFatigue": 1.0,
        "convergence": 1.03
      }
    },
    {
      "pid": 691406,
      "name": "",
      "team": "TB",
      "gameProb": 0.0631,
      "gameMatchup": "TB vs AZ",
      "battingOrder": 3,
      "pitcherName": "Merrill Kelly",
      "grade": "D",
      "factors": {
        "iso": 1.0,
        "platoon": 0.96,
        "park": 1.0,
        "wind": 1.0,
        "temp": 0.93,
        "kTrend": 1.0,
        "bullpen": 1.0,
        "pitFatigue": 1.0,
        "convergence": 1.03
      }
    },
    {
      "pid": 693307,
      "name": "",
      "team": "DET",
      "gameProb": 0.0627,
      "gameMatchup": "DET vs HOU",
      "battingOrder": 4,
      "pitcherName": "Hunter Brown",
      "grade": "D",
      "factors": {
        "iso": 1.0,
        "platoon": 0.96,
        "park": 1.02,
        "wind": 1.0,
        "temp": 0.93,
        "kTrend": 1.0,
        "bullpen": 1.0,
        "pitFatigue": 1.0,
        "convergence": 1.03
      }
    },
    {
      "pid": 678554,
      "name": "",
      "team": "WSH",
      "gameProb": 0.0609,
      "gameMatchup": "WSH @ BAL",
      "battingOrder": 3,
      "pitcherName": "Kyle Bradish",
      "grade": "D",
      "factors": {
        "iso": 1.0,
        "platoon": 0.96,
        "park": 1.0,
        "wind": 1.0,
        "temp": 0.93,
        "kTrend": 1.0,
        "bullpen": 1.0,
        "pitFatigue": 1.0,
        "convergence": 1.03
      }
    },
    {
      "pid": 664040,
      "name": "",
      "team": "PIT",
      "gameProb": 0.0606,
      "gameMatchup": "PIT vs CIN",
      "battingOrder": 2,
      "pitcherName": "Brady Singer",
      "grade": "D",
      "factors": {
        "iso": 1.0,
        "platoon": 0.96,
        "park": 1.0,
        "wind": 1.0,
        "temp": 0.93,
        "kTrend": 1.0,
        "bullpen": 1.0,
        "pitFatigue": 1.0,
        "convergence": 1.03
      }
    },
    {
      "pid": 668709,
      "name": "",
      "team": "CIN",
      "gameProb": 0.0605,
      "gameMatchup": "CIN @ PIT",
      "battingOrder": 3,
      "pitcherName": "Mitch Keller",
      "grade": "D",
      "factors": {
        "iso": 1.0,
        "platoon": 0.96,
        "park": 1.0,
        "wind": 1.0,
        "temp": 0.93,
        "kTrend": 1.0,
        "bullpen": 1.0,
        "pitFatigue": 1.0,
        "convergence": 1.03
      }
    },
    {
      "pid": 695657,
      "name": "",
      "team": "CWS",
      "gameProb": 0.0604,
      "gameMatchup": "CWS vs KC",
      "battingOrder": 5,
      "pitcherName": "Luinder Avila",
      "grade": "D",
      "factors": {
        "iso": 1.0,
        "platoon": 0.96,
        "park": 1.0,
        "wind": 1.0,
        "temp": 0.93,
        "kTrend": 1.0,
        "bullpen": 1.0,
        "pitFatigue": 1.0,
        "convergence": 1.03
      }
    },
    {
      "pid": 695600,
      "name": "",
      "team": "KC",
      "gameProb": 0.0594,
      "gameMatchup": "KC @ CWS",
      "battingOrder": 3,
      "pitcherName": "Anthony Kay",
      "grade": "D",
      "factors": {
        "iso": 1.0,
        "platoon": 1.15,
        "park": 1.0,
        "wind": 1.0,
        "temp": 0.93,
        "kTrend": 1.0,
        "bullpen": 1.0,
        "pitFatigue": 1.0,
        "convergence": 1.06
      }
    },
    {
      "pid": 596142,
      "name": "",
      "team": "MIL",
      "gameProb": 0.0591,
      "gameMatchup": "MIL vs CHC",
      "battingOrder": 6,
      "pitcherName": "Ryan Rolison",
      "grade": "D",
      "factors": {
        "iso": 1.0,
        "platoon": 1.15,
        "park": 1.0,
        "wind": 1.0,
        "temp": 0.93,
        "kTrend": 1.0,
        "bullpen": 1.0,
        "pitFatigue": 1.0,
        "convergence": 1.06
      }
    },
    {
      "pid": 694249,
      "name": "",
      "team": "COL",
      "gameProb": 0.059,
      "gameMatchup": "COL @ MIN",
      "battingOrder": 5,
      "pitcherName": "Connor Prielipp",
      "grade": "D",
      "factors": {
        "iso": 1.0,
        "platoon": 1.15,
        "park": 1.0,
        "wind": 1.0,
        "temp": 0.93,
        "kTrend": 1.0,
        "bullpen": 1.0,
        "pitFatigue": 1.0,
        "convergence": 1.06
      }
    },
    {
      "pid": 681198,
      "name": "",
      "team": "COL",
      "gameProb": 0.0589,
      "gameMatchup": "COL @ MIN",
      "battingOrder": 4,
      "pitcherName": "Connor Prielipp",
      "grade": "D",
      "factors": {
        "iso": 1.0,
        "platoon": 1.15,
        "park": 1.0,
        "wind": 1.0,
        "temp": 0.93,
        "kTrend": 1.0,
        "bullpen": 1.0,
        "pitFatigue": 1.0,
        "convergence": 1.06
      }
    },
    {
      "pid": 669016,
      "name": "",
      "team": "PHI",
      "gameProb": 0.0585,
      "gameMatchup": "PHI @ NYM",
      "battingOrder": 5,
      "pitcherName": "Cionel P\u00e9rez",
      "grade": "D",
      "factors": {
        "iso": 1.0,
        "platoon": 1.15,
        "park": 1.0,
        "wind": 1.0,
        "temp": 0.93,
        "kTrend": 1.0,
        "bullpen": 1.0,
        "pitFatigue": 1.0,
        "convergence": 1.06
      }
    },
    {
      "pid": 672960,
      "name": "",
      "team": "TOR",
      "gameProb": 0.0583,
      "gameMatchup": "TOR vs TEX",
      "battingOrder": 4,
      "pitcherName": "Kumar Rocker",
      "grade": "D",
      "factors": {
        "iso": 1.0,
        "platoon": 0.96,
        "park": 1.0,
        "wind": 1.0,
        "temp": 0.93,
        "kTrend": 1.0,
        "bullpen": 1.0,
        "pitFatigue": 1.0,
        "convergence": 1.03
      }
    },
    {
      "pid": 656537,
      "name": "",
      "team": "PHI",
      "gameProb": 0.0572,
      "gameMatchup": "PHI @ NYM",
      "battingOrder": 8,
      "pitcherName": "Cionel P\u00e9rez",
      "grade": "D",
      "factors": {
        "iso": 1.0,
        "platoon": 1.15,
        "park": 1.0,
        "wind": 1.0,
        "temp": 0.93,
        "kTrend": 1.0,
        "bullpen": 1.0,
        "pitFatigue": 1.0,
        "convergence": 1.06
      }
    },
    {
      "pid": 682626,
      "name": "",
      "team": "NYM",
      "gameProb": 0.0567,
      "gameMatchup": "NYM vs PHI",
      "battingOrder": 5,
      "pitcherName": "Jes\u00fas Luzardo",
      "grade": "D",
      "factors": {
        "iso": 1.0,
        "platoon": 1.15,
        "park": 1.0,
        "wind": 1.0,
        "temp": 0.93,
        "kTrend": 1.0,
        "bullpen": 1.0,
        "pitFatigue": 1.0,
        "convergence": 1.06
      }
    },
    {
      "pid": 668901,
      "name": "",
      "team": "NYM",
      "gameProb": 0.0562,
      "gameMatchup": "NYM vs PHI",
      "battingOrder": 6,
      "pitcherName": "Jes\u00fas Luzardo",
      "grade": "D",
      "factors": {
        "iso": 1.0,
        "platoon": 1.15,
        "park": 1.0,
        "wind": 1.0,
        "temp": 0.93,
        "kTrend": 1.0,
        "bullpen": 1.0,
        "pitFatigue": 1.0,
        "convergence": 1.06
      }
    },
    {
      "pid": 671277,
      "name": "",
      "team": "WSH",
      "gameProb": 0.0559,
      "gameMatchup": "WSH @ BAL",
      "battingOrder": 2,
      "pitcherName": "Kyle Bradish",
      "grade": "D",
      "factors": {
        "iso": 1.0,
        "platoon": 0.96,
        "park": 1.0,
        "wind": 1.0,
        "temp": 0.93,
        "kTrend": 1.0,
        "bullpen": 1.0,
        "pitFatigue": 1.0,
        "convergence": 1.03
      }
    },
    {
      "pid": 695578,
      "name": "",
      "team": "WSH",
      "gameProb": 0.0557,
      "gameMatchup": "WSH @ BAL",
      "battingOrder": 1,
      "pitcherName": "Kyle Bradish",
      "grade": "D",
      "factors": {
        "iso": 1.0,
        "platoon": 0.96,
        "park": 1.0,
        "wind": 1.0,
        "temp": 0.93,
        "kTrend": 1.0,
        "bullpen": 1.0,
        "pitFatigue": 1.0,
        "convergence": 1.03
      }
    },
    {
      "pid": 572233,
      "name": "",
      "team": "HOU",
      "gameProb": 0.0555,
      "gameMatchup": "HOU @ DET",
      "battingOrder": 4,
      "pitcherName": "Jack Flaherty",
      "grade": "D",
      "factors": {
        "iso": 1.0,
        "platoon": 0.96,
        "park": 1.02,
        "wind": 1.0,
        "temp": 0.93,
        "kTrend": 1.0,
        "bullpen": 1.0,
        "pitFatigue": 1.0,
        "convergence": 1.03
      }
    },
    {
      "pid": 678246,
      "name": "",
      "team": "CWS",
      "gameProb": 0.0554,
      "gameMatchup": "CWS vs KC",
      "battingOrder": 2,
      "pitcherName": "Luinder Avila",
      "grade": "D",
      "factors": {
        "iso": 1.0,
        "platoon": 0.96,
        "park": 1.0,
        "wind": 1.0,
        "temp": 0.93,
        "kTrend": 1.0,
        "bullpen": 1.0,
        "pitFatigue": 1.0,
        "convergence": 1.03
      }
    },
    {
      "pid": 681481,
      "name": "",
      "team": "DET",
      "gameProb": 0.0551,
      "gameMatchup": "DET vs HOU",
      "battingOrder": 5,
      "pitcherName": "Hunter Brown",
      "grade": "D",
      "factors": {
        "iso": 1.0,
        "platoon": 0.96,
        "park": 1.02,
        "wind": 1.0,
        "temp": 0.93,
        "kTrend": 1.0,
        "bullpen": 1.0,
        "pitFatigue": 1.0,
        "convergence": 1.03
      }
    },
    {
      "pid": 668930,
      "name": "",
      "team": "MIL",
      "gameProb": 0.0528,
      "gameMatchup": "MIL vs CHC",
      "battingOrder": 3,
      "pitcherName": "Ryan Rolison",
      "grade": "D",
      "factors": {
        "iso": 1.0,
        "platoon": 1.15,
        "park": 1.0,
        "wind": 1.0,
        "temp": 0.93,
        "kTrend": 1.0,
        "bullpen": 1.0,
        "pitFatigue": 1.0,
        "convergence": 1.06
      }
    },
    {
      "pid": 682928,
      "name": "",
      "team": "WSH",
      "gameProb": 0.0525,
      "gameMatchup": "WSH @ BAL",
      "battingOrder": 4,
      "pitcherName": "Kyle Bradish",
      "grade": "D",
      "factors": {
        "iso": 1.0,
        "platoon": 0.96,
        "park": 1.0,
        "wind": 1.0,
        "temp": 0.93,
        "kTrend": 1.0,
        "bullpen": 1.0,
        "pitFatigue": 1.0,
        "convergence": 1.03
      }
    },
    {
      "pid": 691718,
      "name": "",
      "team": "CHC",
      "gameProb": 0.0523,
      "gameMatchup": "CHC @ MIL",
      "battingOrder": 1,
      "pitcherName": "Brandon Woodruff",
      "grade": "D",
      "factors": {
        "iso": 1.0,
        "platoon": 0.96,
        "park": 1.0,
        "wind": 1.0,
        "temp": 0.93,
        "kTrend": 1.0,
        "bullpen": 1.0,
        "pitFatigue": 1.0,
        "convergence": 1.03
      }
    },
    {
      "pid": 624413,
      "name": "",
      "team": "BAL",
      "gameProb": 0.0519,
      "gameMatchup": "BAL vs WSH",
      "battingOrder": 4,
      "pitcherName": "Zack Littell",
      "grade": "D",
      "factors": {
        "iso": 1.0,
        "platoon": 0.96,
        "park": 1.0,
        "wind": 1.0,
        "temp": 0.93,
        "kTrend": 1.0,
        "bullpen": 1.0,
        "pitFatigue": 1.0,
        "convergence": 1.03
      }
    },
    {
      "pid": 592626,
      "name": "",
      "team": "TEX",
      "gameProb": 0.0509,
      "gameMatchup": "TEX @ TOR",
      "battingOrder": 1,
      "pitcherName": "Shane Bieber",
      "grade": "D",
      "factors": {
        "iso": 1.0,
        "platoon": 0.96,
        "park": 1.0,
        "wind": 1.0,
        "temp": 0.93,
        "kTrend": 1.0,
        "bullpen": 1.0,
        "pitFatigue": 1.0,
        "convergence": 1.03
      }
    },
    {
      "pid": 664023,
      "name": "",
      "team": "CHC",
      "gameProb": 0.0505,
      "gameMatchup": "CHC @ MIL",
      "battingOrder": 5,
      "pitcherName": "Brandon Woodruff",
      "grade": "D",
      "factors": {
        "iso": 1.0,
        "platoon": 0.96,
        "park": 1.0,
        "wind": 1.0,
        "temp": 0.93,
        "kTrend": 1.0,
        "bullpen": 1.0,
        "pitFatigue": 1.0,
        "convergence": 1.03
      }
    },
    {
      "pid": 686681,
      "name": "",
      "team": "KC",
      "gameProb": 0.05,
      "gameMatchup": "KC @ CWS",
      "battingOrder": 6,
      "pitcherName": "Anthony Kay",
      "grade": "D",
      "factors": {
        "iso": 1.0,
        "platoon": 1.15,
        "park": 1.0,
        "wind": 1.0,
        "temp": 0.93,
        "kTrend": 1.0,
        "bullpen": 1.0,
        "pitFatigue": 1.0,
        "convergence": 1.06
      }
    },
    {
      "pid": 608369,
      "name": "",
      "team": "TEX",
      "gameProb": 0.0491,
      "gameMatchup": "TEX @ TOR",
      "battingOrder": 3,
      "pitcherName": "Shane Bieber",
      "grade": "D",
      "factors": {
        "iso": 1.0,
        "platoon": 0.96,
        "park": 1.0,
        "wind": 1.0,
        "temp": 0.93,
        "kTrend": 1.0,
        "bullpen": 1.0,
        "pitFatigue": 1.0,
        "convergence": 1.03
      }
    },
    {
      "pid": 682829,
      "name": "",
      "team": "CIN",
      "gameProb": 0.0489,
      "gameMatchup": "CIN @ PIT",
      "battingOrder": 1,
      "pitcherName": "Mitch Keller",
      "grade": "D",
      "factors": {
        "iso": 1.0,
        "platoon": 0.96,
        "park": 1.0,
        "wind": 1.0,
        "temp": 0.93,
        "kTrend": 1.0,
        "bullpen": 1.0,
        "pitFatigue": 1.0,
        "convergence": 1.03
      }
    },
    {
      "pid": 665019,
      "name": "",
      "team": "MIN",
      "gameProb": 0.0488,
      "gameMatchup": "MIN vs COL",
      "battingOrder": 3,
      "pitcherName": "Ryan Feltner",
      "grade": "D",
      "factors": {
        "iso": 1.0,
        "platoon": 0.96,
        "park": 1.0,
        "wind": 1.0,
        "temp": 0.93,
        "kTrend": 1.0,
        "bullpen": 1.0,
        "pitFatigue": 1.0,
        "convergence": 1.03
      }
    },
    {
      "pid": 677951,
      "name": "",
      "team": "KC",
      "gameProb": 0.048,
      "gameMatchup": "KC @ CWS",
      "battingOrder": 2,
      "pitcherName": "Anthony Kay",
      "grade": "D",
      "factors": {
        "iso": 1.0,
        "platoon": 1.15,
        "park": 1.0,
        "wind": 1.0,
        "temp": 0.93,
        "kTrend": 1.0,
        "bullpen": 1.0,
        "pitFatigue": 1.0,
        "convergence": 1.06
      }
    },
    {
      "pid": 694212,
      "name": "",
      "team": "BAL",
      "gameProb": 0.0475,
      "gameMatchup": "BAL vs WSH",
      "battingOrder": 5,
      "pitcherName": "Zack Littell",
      "grade": "D",
      "factors": {
        "iso": 1.0,
        "platoon": 0.96,
        "park": 1.0,
        "wind": 1.0,
        "temp": 0.93,
        "kTrend": 1.0,
        "bullpen": 1.0,
        "pitFatigue": 1.0,
        "convergence": 1.03
      }
    },
    {
      "pid": 806068,
      "name": "",
      "team": "SEA",
      "gameProb": 0.0465,
      "gameMatchup": "SEA @ CLE",
      "battingOrder": 7,
      "pitcherName": "Gavin Williams",
      "grade": "D",
      "factors": {
        "iso": 1.0,
        "platoon": 0.96,
        "park": 1.0,
        "wind": 1.0,
        "temp": 0.93,
        "kTrend": 1.0,
        "bullpen": 1.0,
        "pitFatigue": 1.0,
        "convergence": 1.03
      }
    },
    {
      "pid": 701398,
      "name": "",
      "team": "CIN",
      "gameProb": 0.0463,
      "gameMatchup": "CIN @ PIT",
      "battingOrder": 2,
      "pitcherName": "Mitch Keller",
      "grade": "D",
      "factors": {
        "iso": 1.0,
        "platoon": 0.96,
        "park": 1.0,
        "wind": 1.0,
        "temp": 0.93,
        "kTrend": 1.0,
        "bullpen": 1.0,
        "pitFatigue": 1.0,
        "convergence": 1.03
      }
    },
    {
      "pid": 606466,
      "name": "",
      "team": "AZ",
      "gameProb": 0.0462,
      "gameMatchup": "AZ @ TB",
      "battingOrder": 1,
      "pitcherName": "Drew Rasmussen",
      "grade": "D",
      "factors": {
        "iso": 1.0,
        "platoon": 0.96,
        "park": 1.0,
        "wind": 1.0,
        "temp": 0.93,
        "kTrend": 1.0,
        "bullpen": 1.0,
        "pitFatigue": 1.0,
        "convergence": 1.03
      }
    },
    {
      "pid": 686797,
      "name": "",
      "team": "MIN",
      "gameProb": 0.0455,
      "gameMatchup": "MIN vs COL",
      "battingOrder": 5,
      "pitcherName": "Ryan Feltner",
      "grade": "D",
      "factors": {
        "iso": 1.0,
        "platoon": 0.96,
        "park": 1.0,
        "wind": 1.0,
        "temp": 0.93,
        "kTrend": 1.0,
        "bullpen": 1.0,
        "pitFatigue": 1.0,
        "convergence": 1.03
      }
    },
    {
      "pid": 683002,
      "name": "",
      "team": "BAL",
      "gameProb": 0.0449,
      "gameMatchup": "BAL vs WSH",
      "battingOrder": 2,
      "pitcherName": "Zack Littell",
      "grade": "D",
      "factors": {
        "iso": 1.0,
        "platoon": 0.96,
        "park": 1.0,
        "wind": 1.0,
        "temp": 0.93,
        "kTrend": 1.0,
        "bullpen": 1.0,
        "pitFatigue": 1.0,
        "convergence": 1.03
      }
    },
    {
      "pid": 701807,
      "name": "",
      "team": "NYM",
      "gameProb": 0.0448,
      "gameMatchup": "NYM vs PHI",
      "battingOrder": 1,
      "pitcherName": "Jes\u00fas Luzardo",
      "grade": "D",
      "factors": {
        "iso": 1.0,
        "platoon": 1.15,
        "park": 1.0,
        "wind": 1.0,
        "temp": 0.93,
        "kTrend": 1.0,
        "bullpen": 1.0,
        "pitFatigue": 1.0,
        "convergence": 1.06
      }
    },
    {
      "pid": 682998,
      "name": "",
      "team": "AZ",
      "gameProb": 0.0443,
      "gameMatchup": "AZ @ TB",
      "battingOrder": 3,
      "pitcherName": "Drew Rasmussen",
      "grade": "D",
      "factors": {
        "iso": 1.0,
        "platoon": 0.96,
        "park": 1.0,
        "wind": 1.0,
        "temp": 0.93,
        "kTrend": 1.0,
        "bullpen": 1.0,
        "pitFatigue": 1.0,
        "convergence": 1.03
      }
    },
    {
      "pid": 669394,
      "name": "",
      "team": "TEX",
      "gameProb": 0.0442,
      "gameMatchup": "TEX @ TOR",
      "battingOrder": 5,
      "pitcherName": "Shane Bieber",
      "grade": "D",
      "factors": {
        "iso": 1.0,
        "platoon": 0.96,
        "park": 1.0,
        "wind": 1.0,
        "temp": 0.93,
        "kTrend": 1.0,
        "bullpen": 1.0,
        "pitFatigue": 1.0,
        "convergence": 1.03
      }
    },
    {
      "pid": 666182,
      "name": "",
      "team": "NYM",
      "gameProb": 0.0442,
      "gameMatchup": "NYM vs PHI",
      "battingOrder": 3,
      "pitcherName": "Jes\u00fas Luzardo",
      "grade": "D",
      "factors": {
        "iso": 1.0,
        "platoon": 1.15,
        "park": 1.0,
        "wind": 1.0,
        "temp": 0.93,
        "kTrend": 1.0,
        "bullpen": 1.0,
        "pitFatigue": 1.0,
        "convergence": 1.06
      }
    },
    {
      "pid": 673548,
      "name": "",
      "team": "CHC",
      "gameProb": 0.044,
      "gameMatchup": "CHC @ MIL",
      "battingOrder": 4,
      "pitcherName": "Brandon Woodruff",
      "grade": "D",
      "factors": {
        "iso": 1.0,
        "platoon": 0.96,
        "park": 1.0,
        "wind": 1.0,
        "temp": 0.93,
        "kTrend": 1.0,
        "bullpen": 1.0,
        "pitFatigue": 1.0,
        "convergence": 1.03
      }
    },
    {
      "pid": 699013,
      "name": "",
      "team": "PIT",
      "gameProb": 0.0436,
      "gameMatchup": "PIT vs CIN",
      "battingOrder": 6,
      "pitcherName": "Brady Singer",
      "grade": "D",
      "factors": {
        "iso": 1.0,
        "platoon": 0.96,
        "park": 1.0,
        "wind": 1.0,
        "temp": 0.93,
        "kTrend": 1.0,
        "bullpen": 1.0,
        "pitFatigue": 1.0,
        "convergence": 1.03
      }
    },
    {
      "pid": 521692,
      "name": "",
      "team": "KC",
      "gameProb": 0.0433,
      "gameMatchup": "KC @ CWS",
      "battingOrder": 5,
      "pitcherName": "Anthony Kay",
      "grade": "D",
      "factors": {
        "iso": 1.0,
        "platoon": 1.15,
        "park": 1.0,
        "wind": 1.0,
        "temp": 0.93,
        "kTrend": 1.0,
        "bullpen": 1.0,
        "pitFatigue": 1.0,
        "convergence": 1.03
      }
    },
    {
      "pid": 668715,
      "name": "",
      "team": "CIN",
      "gameProb": 0.0431,
      "gameMatchup": "CIN @ PIT",
      "battingOrder": 5,
      "pitcherName": "Mitch Keller",
      "grade": "D",
      "factors": {
        "iso": 1.0,
        "platoon": 0.96,
        "park": 1.0,
        "wind": 1.0,
        "temp": 0.93,
        "kTrend": 1.0,
        "bullpen": 1.0,
        "pitFatigue": 1.0,
        "convergence": 1.03
      }
    },
    {
      "pid": 643217,
      "name": "",
      "team": "CWS",
      "gameProb": 0.0431,
      "gameMatchup": "CWS vs KC",
      "battingOrder": 4,
      "pitcherName": "Luinder Avila",
      "grade": "D",
      "factors": {
        "iso": 1.0,
        "platoon": 0.96,
        "park": 1.0,
        "wind": 1.0,
        "temp": 0.93,
        "kTrend": 1.0,
        "bullpen": 1.0,
        "pitFatigue": 1.0,
        "convergence": 1.03
      }
    },
    {
      "pid": 676475,
      "name": "",
      "team": "STL",
      "gameProb": 0.0429,
      "gameMatchup": "STL vs MIA",
      "battingOrder": 3,
      "pitcherName": "Tyler Phillips",
      "grade": "D",
      "factors": {
        "iso": 1.0,
        "platoon": 0.96,
        "park": 1.0,
        "wind": 1.0,
        "temp": 0.93,
        "kTrend": 1.0,
        "bullpen": 1.0,
        "pitFatigue": 1.0,
        "convergence": 1.03
      }
    },
    {
      "pid": 664761,
      "name": "",
      "team": "PHI",
      "gameProb": 0.0428,
      "gameMatchup": "PHI @ NYM",
      "battingOrder": 4,
      "pitcherName": "Cionel P\u00e9rez",
      "grade": "D",
      "factors": {
        "iso": 1.0,
        "platoon": 1.15,
        "park": 1.0,
        "wind": 1.0,
        "temp": 0.93,
        "kTrend": 1.0,
        "bullpen": 1.0,
        "pitFatigue": 1.0,
        "convergence": 1.03
      }
    },
    {
      "pid": 668939,
      "name": "",
      "team": "BAL",
      "gameProb": 0.0411,
      "gameMatchup": "BAL vs WSH",
      "battingOrder": 3,
      "pitcherName": "Zack Littell",
      "grade": "D",
      "factors": {
        "iso": 1.0,
        "platoon": 0.96,
        "park": 1.0,
        "wind": 1.0,
        "temp": 0.93,
        "kTrend": 1.0,
        "bullpen": 1.0,
        "pitFatigue": 1.0,
        "convergence": 1.03
      }
    },
    {
      "pid": 677594,
      "name": "",
      "team": "SEA",
      "gameProb": 0.0411,
      "gameMatchup": "SEA @ CLE",
      "battingOrder": 2,
      "pitcherName": "Gavin Williams",
      "grade": "D",
      "factors": {
        "iso": 1.0,
        "platoon": 0.96,
        "park": 1.0,
        "wind": 1.0,
        "temp": 0.93,
        "kTrend": 1.0,
        "bullpen": 1.0,
        "pitFatigue": 1.0,
        "convergence": 1.03
      }
    },
    {
      "pid": 666018,
      "name": "",
      "team": "TB",
      "gameProb": 0.0408,
      "gameMatchup": "TB vs AZ",
      "battingOrder": 2,
      "pitcherName": "Merrill Kelly",
      "grade": "D",
      "factors": {
        "iso": 1.0,
        "platoon": 0.96,
        "park": 1.0,
        "wind": 1.0,
        "temp": 0.93,
        "kTrend": 1.0,
        "bullpen": 1.0,
        "pitFatigue": 1.0,
        "convergence": 1.03
      }
    },
    {
      "pid": 681715,
      "name": "",
      "team": "MIA",
      "gameProb": 0.0408,
      "gameMatchup": "MIA @ STL",
      "battingOrder": 5,
      "pitcherName": "Kyle Leahy",
      "grade": "D",
      "factors": {
        "iso": 1.0,
        "platoon": 0.96,
        "park": 1.0,
        "wind": 1.0,
        "temp": 0.93,
        "kTrend": 1.0,
        "bullpen": 1.0,
        "pitFatigue": 1.0,
        "convergence": 1.03
      }
    },
    {
      "pid": 592885,
      "name": "",
      "team": "MIL",
      "gameProb": 0.0406,
      "gameMatchup": "MIL vs CHC",
      "battingOrder": 1,
      "pitcherName": "Ryan Rolison",
      "grade": "D",
      "factors": {
        "iso": 1.0,
        "platoon": 1.15,
        "park": 1.0,
        "wind": 1.0,
        "temp": 0.93,
        "kTrend": 1.0,
        "bullpen": 1.0,
        "pitFatigue": 1.0,
        "convergence": 1.06
      }
    },
    {
      "pid": 650490,
      "name": "",
      "team": "TB",
      "gameProb": 0.0404,
      "gameMatchup": "TB vs AZ",
      "battingOrder": 1,
      "pitcherName": "Merrill Kelly",
      "grade": "D",
      "factors": {
        "iso": 1.0,
        "platoon": 0.96,
        "park": 1.0,
        "wind": 1.0,
        "temp": 0.93,
        "kTrend": 1.0,
        "bullpen": 1.0,
        "pitFatigue": 1.0,
        "convergence": 1.03
      }
    },
    {
      "pid": 691723,
      "name": "",
      "team": "BAL",
      "gameProb": 0.0402,
      "gameMatchup": "BAL vs WSH",
      "battingOrder": 7,
      "pitcherName": "Zack Littell",
      "grade": "D",
      "factors": {
        "iso": 1.0,
        "platoon": 0.96,
        "park": 1.0,
        "wind": 1.0,
        "temp": 0.93,
        "kTrend": 1.0,
        "bullpen": 1.0,
        "pitFatigue": 1.0,
        "convergence": 1.03
      }
    },
    {
      "pid": 656811,
      "name": "",
      "team": "PIT",
      "gameProb": 0.0402,
      "gameMatchup": "PIT vs CIN",
      "battingOrder": 5,
      "pitcherName": "Brady Singer",
      "grade": "D",
      "factors": {
        "iso": 1.0,
        "platoon": 0.96,
        "park": 1.0,
        "wind": 1.0,
        "temp": 0.93,
        "kTrend": 1.0,
        "bullpen": 1.0,
        "pitFatigue": 1.0,
        "convergence": 1.03
      }
    },
    {
      "pid": 690924,
      "name": "",
      "team": "COL",
      "gameProb": 0.0399,
      "gameMatchup": "COL @ MIN",
      "battingOrder": 8,
      "pitcherName": "Connor Prielipp",
      "grade": "D",
      "factors": {
        "iso": 1.0,
        "platoon": 1.15,
        "park": 1.0,
        "wind": 1.0,
        "temp": 0.93,
        "kTrend": 1.0,
        "bullpen": 1.0,
        "pitFatigue": 1.0,
        "convergence": 1.06
      }
    },
    {
      "pid": 621438,
      "name": "",
      "team": "NYM",
      "gameProb": 0.0396,
      "gameMatchup": "NYM vs PHI",
      "battingOrder": 7,
      "pitcherName": "Jes\u00fas Luzardo",
      "grade": "D",
      "factors": {
        "iso": 1.0,
        "platoon": 1.15,
        "park": 1.0,
        "wind": 1.0,
        "temp": 0.93,
        "kTrend": 1.0,
        "bullpen": 1.0,
        "pitFatigue": 1.0,
        "convergence": 1.06
      }
    },
    {
      "pid": 553993,
      "name": "",
      "team": "CIN",
      "gameProb": 0.0391,
      "gameMatchup": "CIN @ PIT",
      "battingOrder": 4,
      "pitcherName": "Mitch Keller",
      "grade": "D",
      "factors": {
        "iso": 1.0,
        "platoon": 0.96,
        "park": 1.0,
        "wind": 1.0,
        "temp": 0.93,
        "kTrend": 1.0,
        "bullpen": 1.0,
        "pitFatigue": 1.0,
        "convergence": 1.03
      }
    },
    {
      "pid": 683748,
      "name": "",
      "team": "TB",
      "gameProb": 0.0388,
      "gameMatchup": "TB vs AZ",
      "battingOrder": 4,
      "pitcherName": "Merrill Kelly",
      "grade": "D",
      "factors": {
        "iso": 1.0,
        "platoon": 0.96,
        "park": 1.0,
        "wind": 1.0,
        "temp": 0.93,
        "kTrend": 1.0,
        "bullpen": 1.0,
        "pitFatigue": 1.0,
        "convergence": 1.03
      }
    },
    {
      "pid": 641487,
      "name": "",
      "team": "SEA",
      "gameProb": 0.0387,
      "gameMatchup": "SEA @ CLE",
      "battingOrder": 1,
      "pitcherName": "Gavin Williams",
      "grade": "D",
      "factors": {
        "iso": 1.0,
        "platoon": 0.96,
        "park": 1.0,
        "wind": 1.0,
        "temp": 0.93,
        "kTrend": 1.0,
        "bullpen": 1.0,
        "pitFatigue": 1.0,
        "convergence": 1.03
      }
    },
    {
      "pid": 657041,
      "name": "",
      "team": "KC",
      "gameProb": 0.0381,
      "gameMatchup": "KC @ CWS",
      "battingOrder": 1,
      "pitcherName": "Anthony Kay",
      "grade": "D",
      "factors": {
        "iso": 1.0,
        "platoon": 1.15,
        "park": 1.0,
        "wind": 1.0,
        "temp": 0.93,
        "kTrend": 1.0,
        "bullpen": 1.0,
        "pitFatigue": 1.0,
        "convergence": 1.03
      }
    },
    {
      "pid": 683357,
      "name": "",
      "team": "MIA",
      "gameProb": 0.0378,
      "gameMatchup": "MIA @ STL",
      "battingOrder": 7,
      "pitcherName": "Kyle Leahy",
      "grade": "D",
      "factors": {
        "iso": 1.0,
        "platoon": 0.96,
        "park": 1.0,
        "wind": 1.0,
        "temp": 0.93,
        "kTrend": 1.0,
        "bullpen": 1.0,
        "pitFatigue": 1.0,
        "convergence": 1.03
      }
    },
    {
      "pid": 802139,
      "name": "",
      "team": "STL",
      "gameProb": 0.0375,
      "gameMatchup": "STL vs MIA",
      "battingOrder": 1,
      "pitcherName": "Tyler Phillips",
      "grade": "D",
      "factors": {
        "iso": 1.0,
        "platoon": 0.96,
        "park": 1.0,
        "wind": 1.0,
        "temp": 0.93,
        "kTrend": 1.0,
        "bullpen": 1.0,
        "pitFatigue": 1.0,
        "convergence": 1.03
      }
    },
    {
      "pid": 669065,
      "name": "",
      "team": "MIA",
      "gameProb": 0.0374,
      "gameMatchup": "MIA @ STL",
      "battingOrder": 3,
      "pitcherName": "Kyle Leahy",
      "grade": "D",
      "factors": {
        "iso": 1.0,
        "platoon": 0.96,
        "park": 1.0,
        "wind": 1.0,
        "temp": 0.93,
        "kTrend": 1.0,
        "bullpen": 1.0,
        "pitFatigue": 1.0,
        "convergence": 1.03
      }
    },
    {
      "pid": 624424,
      "name": "",
      "team": "CHC",
      "gameProb": 0.0368,
      "gameMatchup": "CHC @ MIL",
      "battingOrder": 7,
      "pitcherName": "Brandon Woodruff",
      "grade": "D",
      "factors": {
        "iso": 1.0,
        "platoon": 0.96,
        "park": 1.0,
        "wind": 1.0,
        "temp": 0.93,
        "kTrend": 1.0,
        "bullpen": 1.0,
        "pitFatigue": 1.0,
        "convergence": 1.03
      }
    },
    {
      "pid": 683734,
      "name": "",
      "team": "MIL",
      "gameProb": 0.0367,
      "gameMatchup": "MIL vs CHC",
      "battingOrder": 4,
      "pitcherName": "Ryan Rolison",
      "grade": "D",
      "factors": {
        "iso": 1.0,
        "platoon": 1.15,
        "park": 1.0,
        "wind": 1.0,
        "temp": 0.93,
        "kTrend": 1.0,
        "bullpen": 1.0,
        "pitFatigue": 1.0,
        "convergence": 1.06
      }
    },
    {
      "pid": 668952,
      "name": "",
      "team": "MIN",
      "gameProb": 0.0366,
      "gameMatchup": "MIN vs COL",
      "battingOrder": 7,
      "pitcherName": "Ryan Feltner",
      "grade": "D",
      "factors": {
        "iso": 1.0,
        "platoon": 0.96,
        "park": 1.0,
        "wind": 1.0,
        "temp": 0.93,
        "kTrend": 1.0,
        "bullpen": 1.0,
        "pitFatigue": 1.0,
        "convergence": 1.03
      }
    },
    {
      "pid": 668904,
      "name": "",
      "team": "MIN",
      "gameProb": 0.0365,
      "gameMatchup": "MIN vs COL",
      "battingOrder": 4,
      "pitcherName": "Ryan Feltner",
      "grade": "D",
      "factors": {
        "iso": 1.0,
        "platoon": 0.96,
        "park": 1.0,
        "wind": 1.0,
        "temp": 0.93,
        "kTrend": 1.0,
        "bullpen": 1.0,
        "pitFatigue": 1.0,
        "convergence": 1.03
      }
    },
    {
      "pid": 668804,
      "name": "",
      "team": "PIT",
      "gameProb": 0.0361,
      "gameMatchup": "PIT vs CIN",
      "battingOrder": 3,
      "pitcherName": "Brady Singer",
      "grade": "D",
      "factors": {
        "iso": 1.0,
        "platoon": 0.96,
        "park": 1.0,
        "wind": 1.0,
        "temp": 0.93,
        "kTrend": 1.0,
        "bullpen": 1.0,
        "pitFatigue": 1.0,
        "convergence": 1.03
      }
    },
    {
      "pid": 700932,
      "name": "",
      "team": "CLE",
      "gameProb": 0.0361,
      "gameMatchup": "CLE vs SEA",
      "battingOrder": 4,
      "pitcherName": "Emerson Hancock",
      "grade": "D",
      "factors": {
        "iso": 1.0,
        "platoon": 0.96,
        "park": 1.0,
        "wind": 1.0,
        "temp": 0.93,
        "kTrend": 1.0,
        "bullpen": 1.0,
        "pitFatigue": 1.0,
        "convergence": 1.03
      }
    },
    {
      "pid": 650489,
      "name": "",
      "team": "COL",
      "gameProb": 0.0361,
      "gameMatchup": "COL @ MIN",
      "battingOrder": 1,
      "pitcherName": "Connor Prielipp",
      "grade": "D",
      "factors": {
        "iso": 1.0,
        "platoon": 1.15,
        "park": 1.0,
        "wind": 1.0,
        "temp": 0.93,
        "kTrend": 1.0,
        "bullpen": 1.0,
        "pitFatigue": 1.0,
        "convergence": 1.03
      }
    },
    {
      "pid": 683953,
      "name": "",
      "team": "CLE",
      "gameProb": 0.0359,
      "gameMatchup": "CLE vs SEA",
      "battingOrder": 2,
      "pitcherName": "Emerson Hancock",
      "grade": "D",
      "factors": {
        "iso": 1.0,
        "platoon": 0.96,
        "park": 1.0,
        "wind": 1.0,
        "temp": 0.93,
        "kTrend": 1.0,
        "bullpen": 1.0,
        "pitFatigue": 1.0,
        "convergence": 1.03
      }
    },
    {
      "pid": 682622,
      "name": "",
      "team": "CIN",
      "gameProb": 0.0357,
      "gameMatchup": "CIN @ PIT",
      "battingOrder": 6,
      "pitcherName": "Mitch Keller",
      "grade": "D",
      "factors": {
        "iso": 1.0,
        "platoon": 0.96,
        "park": 1.0,
        "wind": 1.0,
        "temp": 0.93,
        "kTrend": 1.0,
        "bullpen": 1.0,
        "pitFatigue": 1.0,
        "convergence": 1.03
      }
    },
    {
      "pid": 670623,
      "name": "",
      "team": "HOU",
      "gameProb": 0.0357,
      "gameMatchup": "HOU @ DET",
      "battingOrder": 3,
      "pitcherName": "Jack Flaherty",
      "grade": "D",
      "factors": {
        "iso": 1.0,
        "platoon": 0.96,
        "park": 1.02,
        "wind": 1.0,
        "temp": 0.93,
        "kTrend": 1.0,
        "bullpen": 1.0,
        "pitFatigue": 1.0,
        "convergence": 1.03
      }
    },
    {
      "pid": 681082,
      "name": "",
      "team": "PHI",
      "gameProb": 0.0357,
      "gameMatchup": "PHI @ NYM",
      "battingOrder": 7,
      "pitcherName": "Cionel P\u00e9rez",
      "grade": "D",
      "factors": {
        "iso": 1.0,
        "platoon": 1.15,
        "park": 1.0,
        "wind": 1.0,
        "temp": 0.93,
        "kTrend": 1.0,
        "bullpen": 1.0,
        "pitFatigue": 1.0,
        "convergence": 1.06
      }
    },
    {
      "pid": 686611,
      "name": "",
      "team": "WSH",
      "gameProb": 0.0355,
      "gameMatchup": "WSH @ BAL",
      "battingOrder": 5,
      "pitcherName": "Kyle Bradish",
      "grade": "D",
      "factors": {
        "iso": 1.0,
        "platoon": 0.96,
        "park": 1.0,
        "wind": 1.0,
        "temp": 0.93,
        "kTrend": 1.0,
        "bullpen": 1.0,
        "pitFatigue": 1.0,
        "convergence": 1.03
      }
    },
    {
      "pid": 665161,
      "name": "",
      "team": "HOU",
      "gameProb": 0.0353,
      "gameMatchup": "HOU @ DET",
      "battingOrder": 1,
      "pitcherName": "Jack Flaherty",
      "grade": "D",
      "factors": {
        "iso": 1.0,
        "platoon": 0.96,
        "park": 1.02,
        "wind": 1.0,
        "temp": 0.93,
        "kTrend": 1.0,
        "bullpen": 1.0,
        "pitFatigue": 1.0,
        "convergence": 1.03
      }
    },
    {
      "pid": 663728,
      "name": "",
      "team": "SEA",
      "gameProb": 0.0352,
      "gameMatchup": "SEA @ CLE",
      "battingOrder": 5,
      "pitcherName": "Gavin Williams",
      "grade": "D",
      "factors": {
        "iso": 1.0,
        "platoon": 0.96,
        "park": 1.0,
        "wind": 1.0,
        "temp": 0.93,
        "kTrend": 1.0,
        "bullpen": 1.0,
        "pitFatigue": 1.0,
        "convergence": 1.03
      }
    },
    {
      "pid": 681297,
      "name": "",
      "team": "BAL",
      "gameProb": 0.0351,
      "gameMatchup": "BAL vs WSH",
      "battingOrder": 8,
      "pitcherName": "Zack Littell",
      "grade": "D",
      "factors": {
        "iso": 1.0,
        "platoon": 0.96,
        "park": 1.0,
        "wind": 1.0,
        "temp": 0.93,
        "kTrend": 1.0,
        "bullpen": 1.0,
        "pitFatigue": 1.0,
        "convergence": 1.03
      }
    },
    {
      "pid": 665052,
      "name": "",
      "team": "MIA",
      "gameProb": 0.0345,
      "gameMatchup": "MIA @ STL",
      "battingOrder": 6,
      "pitcherName": "Kyle Leahy",
      "grade": "D",
      "factors": {
        "iso": 1.0,
        "platoon": 0.96,
        "park": 1.0,
        "wind": 1.0,
        "temp": 0.93,
        "kTrend": 1.0,
        "bullpen": 1.0,
        "pitFatigue": 1.0,
        "convergence": 1.03
      }
    },
    {
      "pid": 663494,
      "name": "",
      "team": "STL",
      "gameProb": 0.0341,
      "gameMatchup": "STL vs MIA",
      "battingOrder": 6,
      "pitcherName": "Tyler Phillips",
      "grade": "D",
      "factors": {
        "iso": 1.0,
        "platoon": 0.96,
        "park": 1.0,
        "wind": 1.0,
        "temp": 0.93,
        "kTrend": 1.0,
        "bullpen": 1.0,
        "pitFatigue": 1.0,
        "convergence": 1.03
      }
    },
    {
      "pid": 543807,
      "name": "",
      "team": "TOR",
      "gameProb": 0.034,
      "gameMatchup": "TOR vs TEX",
      "battingOrder": 1,
      "pitcherName": "Kumar Rocker",
      "grade": "D",
      "factors": {
        "iso": 1.0,
        "platoon": 0.96,
        "park": 1.0,
        "wind": 1.0,
        "temp": 0.93,
        "kTrend": 1.0,
        "bullpen": 1.0,
        "pitFatigue": 1.0,
        "convergence": 1.03
      }
    },
    {
      "pid": 702616,
      "name": "",
      "team": "BAL",
      "gameProb": 0.0339,
      "gameMatchup": "BAL vs WSH",
      "battingOrder": 9,
      "pitcherName": "Zack Littell",
      "grade": "D",
      "factors": {
        "iso": 1.0,
        "platoon": 0.96,
        "park": 1.0,
        "wind": 1.0,
        "temp": 0.93,
        "kTrend": 1.0,
        "bullpen": 1.0,
        "pitFatigue": 1.0,
        "convergence": 1.03
      }
    },
    {
      "pid": 680779,
      "name": "",
      "team": "PIT",
      "gameProb": 0.0338,
      "gameMatchup": "PIT vs CIN",
      "battingOrder": 9,
      "pitcherName": "Brady Singer",
      "grade": "D",
      "factors": {
        "iso": 1.0,
        "platoon": 0.96,
        "park": 1.0,
        "wind": 1.0,
        "temp": 0.93,
        "kTrend": 1.0,
        "bullpen": 1.0,
        "pitFatigue": 1.0,
        "convergence": 1.03
      }
    },
    {
      "pid": 621020,
      "name": "",
      "team": "CHC",
      "gameProb": 0.0337,
      "gameMatchup": "CHC @ MIL",
      "battingOrder": 9,
      "pitcherName": "Brandon Woodruff",
      "grade": "D",
      "factors": {
        "iso": 1.0,
        "platoon": 0.96,
        "park": 1.0,
        "wind": 1.0,
        "temp": 0.93,
        "kTrend": 1.0,
        "bullpen": 1.0,
        "pitFatigue": 1.0,
        "convergence": 1.03
      }
    },
    {
      "pid": 592663,
      "name": "",
      "team": "PHI",
      "gameProb": 0.0335,
      "gameMatchup": "PHI @ NYM",
      "battingOrder": 6,
      "pitcherName": "Cionel P\u00e9rez",
      "grade": "D",
      "factors": {
        "iso": 1.0,
        "platoon": 1.15,
        "park": 1.0,
        "wind": 1.0,
        "temp": 0.93,
        "kTrend": 1.0,
        "bullpen": 1.0,
        "pitFatigue": 1.0,
        "convergence": 1.03
      }
    },
    {
      "pid": 660688,
      "name": "",
      "team": "WSH",
      "gameProb": 0.0334,
      "gameMatchup": "WSH @ BAL",
      "battingOrder": 9,
      "pitcherName": "Kyle Bradish",
      "grade": "D",
      "factors": {
        "iso": 1.0,
        "platoon": 0.96,
        "park": 1.0,
        "wind": 1.0,
        "temp": 0.93,
        "kTrend": 1.0,
        "bullpen": 1.0,
        "pitFatigue": 1.0,
        "convergence": 1.03
      }
    },
    {
      "pid": 607208,
      "name": "",
      "team": "PHI",
      "gameProb": 0.0333,
      "gameMatchup": "PHI @ NYM",
      "battingOrder": 1,
      "pitcherName": "Cionel P\u00e9rez",
      "grade": "D",
      "factors": {
        "iso": 1.0,
        "platoon": 1.15,
        "park": 1.0,
        "wind": 1.0,
        "temp": 0.93,
        "kTrend": 1.0,
        "bullpen": 1.0,
        "pitFatigue": 1.0,
        "convergence": 1.03
      }
    },
    {
      "pid": 553869,
      "name": "",
      "team": "TEX",
      "gameProb": 0.0331,
      "gameMatchup": "TEX @ TOR",
      "battingOrder": 8,
      "pitcherName": "Shane Bieber",
      "grade": "D",
      "factors": {
        "iso": 1.0,
        "platoon": 0.96,
        "park": 1.0,
        "wind": 1.0,
        "temp": 0.93,
        "kTrend": 1.0,
        "bullpen": 1.0,
        "pitFatigue": 1.0,
        "convergence": 1.03
      }
    },
    {
      "pid": 663457,
      "name": "",
      "team": "STL",
      "gameProb": 0.033,
      "gameMatchup": "STL vs MIA",
      "battingOrder": 4,
      "pitcherName": "Tyler Phillips",
      "grade": "D",
      "factors": {
        "iso": 1.0,
        "platoon": 0.96,
        "park": 1.0,
        "wind": 1.0,
        "temp": 0.93,
        "kTrend": 1.0,
        "bullpen": 1.0,
        "pitFatigue": 1.0,
        "convergence": 1.03
      }
    },
    {
      "pid": 682997,
      "name": "",
      "team": "PIT",
      "gameProb": 0.0329,
      "gameMatchup": "PIT vs CIN",
      "battingOrder": 7,
      "pitcherName": "Brady Singer",
      "grade": "D",
      "factors": {
        "iso": 1.0,
        "platoon": 0.96,
        "park": 1.0,
        "wind": 1.0,
        "temp": 0.93,
        "kTrend": 1.0,
        "bullpen": 1.0,
        "pitFatigue": 1.0,
        "convergence": 1.03
      }
    },
    {
      "pid": 682818,
      "name": "",
      "team": "TOR",
      "gameProb": 0.0328,
      "gameMatchup": "TOR vs TEX",
      "battingOrder": 8,
      "pitcherName": "Kumar Rocker",
      "grade": "D",
      "factors": {
        "iso": 1.0,
        "platoon": 0.96,
        "park": 1.0,
        "wind": 1.0,
        "temp": 0.93,
        "kTrend": 1.0,
        "bullpen": 1.0,
        "pitFatigue": 1.0,
        "convergence": 1.03
      }
    },
    {
      "pid": 695731,
      "name": "",
      "team": "CWS",
      "gameProb": 0.0318,
      "gameMatchup": "CWS vs KC",
      "battingOrder": 7,
      "pitcherName": "Luinder Avila",
      "grade": "D",
      "factors": {
        "iso": 1.0,
        "platoon": 0.96,
        "park": 1.0,
        "wind": 1.0,
        "temp": 0.93,
        "kTrend": 1.0,
        "bullpen": 1.0,
        "pitFatigue": 1.0,
        "convergence": 1.03
      }
    },
    {
      "pid": 671056,
      "name": "",
      "team": "STL",
      "gameProb": 0.0315,
      "gameMatchup": "STL vs MIA",
      "battingOrder": 2,
      "pitcherName": "Tyler Phillips",
      "grade": "D",
      "factors": {
        "iso": 1.0,
        "platoon": 0.96,
        "park": 1.0,
        "wind": 1.0,
        "temp": 0.93,
        "kTrend": 1.0,
        "bullpen": 1.0,
        "pitFatigue": 1.0,
        "convergence": 1.03
      }
    },
    {
      "pid": 691720,
      "name": "",
      "team": "COL",
      "gameProb": 0.0314,
      "gameMatchup": "COL @ MIN",
      "battingOrder": 6,
      "pitcherName": "Connor Prielipp",
      "grade": "D",
      "factors": {
        "iso": 1.0,
        "platoon": 1.15,
        "park": 1.0,
        "wind": 1.0,
        "temp": 0.93,
        "kTrend": 1.0,
        "bullpen": 1.0,
        "pitFatigue": 1.0,
        "convergence": 1.06
      }
    },
    {
      "pid": 682985,
      "name": "",
      "team": "DET",
      "gameProb": 0.0307,
      "gameMatchup": "DET vs HOU",
      "battingOrder": 3,
      "pitcherName": "Hunter Brown",
      "grade": "D",
      "factors": {
        "iso": 1.0,
        "platoon": 0.96,
        "park": 1.02,
        "wind": 1.0,
        "temp": 0.93,
        "kTrend": 1.0,
        "bullpen": 1.0,
        "pitFatigue": 1.0,
        "convergence": 1.03
      }
    },
    {
      "pid": 800050,
      "name": "",
      "team": "CLE",
      "gameProb": 0.0303,
      "gameMatchup": "CLE vs SEA",
      "battingOrder": 3,
      "pitcherName": "Emerson Hancock",
      "grade": "D",
      "factors": {
        "iso": 1.0,
        "platoon": 0.96,
        "park": 1.0,
        "wind": 1.0,
        "temp": 0.93,
        "kTrend": 1.0,
        "bullpen": 1.0,
        "pitFatigue": 1.0,
        "convergence": 1.03
      }
    },
    {
      "pid": 662139,
      "name": "",
      "team": "TOR",
      "gameProb": 0.0302,
      "gameMatchup": "TOR vs TEX",
      "battingOrder": 5,
      "pitcherName": "Kumar Rocker",
      "grade": "D",
      "factors": {
        "iso": 1.0,
        "platoon": 0.96,
        "park": 1.0,
        "wind": 1.0,
        "temp": 0.93,
        "kTrend": 1.0,
        "bullpen": 1.0,
        "pitFatigue": 1.0,
        "convergence": 1.03
      }
    },
    {
      "pid": 678662,
      "name": "",
      "team": "COL",
      "gameProb": 0.0299,
      "gameMatchup": "COL @ MIN",
      "battingOrder": 9,
      "pitcherName": "Connor Prielipp",
      "grade": "D",
      "factors": {
        "iso": 1.0,
        "platoon": 1.15,
        "park": 1.0,
        "wind": 1.0,
        "temp": 0.93,
        "kTrend": 1.0,
        "bullpen": 1.0,
        "pitFatigue": 1.0,
        "convergence": 1.03
      }
    },
    {
      "pid": 672356,
      "name": "",
      "team": "CLE",
      "gameProb": 0.0298,
      "gameMatchup": "CLE vs SEA",
      "battingOrder": 8,
      "pitcherName": "Emerson Hancock",
      "grade": "D",
      "factors": {
        "iso": 1.0,
        "platoon": 0.96,
        "park": 1.0,
        "wind": 1.0,
        "temp": 0.93,
        "kTrend": 1.0,
        "bullpen": 1.0,
        "pitFatigue": 1.0,
        "convergence": 1.03
      }
    },
    {
      "pid": 672386,
      "name": "",
      "team": "TOR",
      "gameProb": 0.0296,
      "gameMatchup": "TOR vs TEX",
      "battingOrder": 7,
      "pitcherName": "Kumar Rocker",
      "grade": "D",
      "factors": {
        "iso": 1.0,
        "platoon": 0.96,
        "park": 1.0,
        "wind": 1.0,
        "temp": 0.93,
        "kTrend": 1.0,
        "bullpen": 1.0,
        "pitFatigue": 1.0,
        "convergence": 1.03
      }
    },
    {
      "pid": 668227,
      "name": "",
      "team": "SEA",
      "gameProb": 0.0293,
      "gameMatchup": "SEA @ CLE",
      "battingOrder": 4,
      "pitcherName": "Gavin Williams",
      "grade": "D",
      "factors": {
        "iso": 1.0,
        "platoon": 0.96,
        "park": 1.0,
        "wind": 1.0,
        "temp": 0.93,
        "kTrend": 1.0,
        "bullpen": 1.0,
        "pitFatigue": 1.0,
        "convergence": 1.03
      }
    },
    {
      "pid": 694371,
      "name": "",
      "team": "AZ",
      "gameProb": 0.0293,
      "gameMatchup": "AZ @ TB",
      "battingOrder": 9,
      "pitcherName": "Drew Rasmussen",
      "grade": "D",
      "factors": {
        "iso": 1.0,
        "platoon": 0.96,
        "park": 1.0,
        "wind": 1.0,
        "temp": 0.93,
        "kTrend": 1.0,
        "bullpen": 1.0,
        "pitFatigue": 1.0,
        "convergence": 1.03
      }
    },
    {
      "pid": 683737,
      "name": "",
      "team": "CHC",
      "gameProb": 0.0293,
      "gameMatchup": "CHC @ MIL",
      "battingOrder": 3,
      "pitcherName": "Brandon Woodruff",
      "grade": "D",
      "factors": {
        "iso": 1.0,
        "platoon": 0.96,
        "park": 1.0,
        "wind": 1.0,
        "temp": 0.93,
        "kTrend": 1.0,
        "bullpen": 1.0,
        "pitFatigue": 1.0,
        "convergence": 1.03
      }
    },
    {
      "pid": 696285,
      "name": "",
      "team": "WSH",
      "gameProb": 0.029,
      "gameMatchup": "WSH @ BAL",
      "battingOrder": 7,
      "pitcherName": "Kyle Bradish",
      "grade": "D",
      "factors": {
        "iso": 1.0,
        "platoon": 0.96,
        "park": 1.0,
        "wind": 1.0,
        "temp": 0.93,
        "kTrend": 1.0,
        "bullpen": 1.0,
        "pitFatigue": 1.0,
        "convergence": 1.03
      }
    },
    {
      "pid": 673962,
      "name": "",
      "team": "TEX",
      "gameProb": 0.0284,
      "gameMatchup": "TEX @ TOR",
      "battingOrder": 2,
      "pitcherName": "Shane Bieber",
      "grade": "D",
      "factors": {
        "iso": 1.0,
        "platoon": 0.96,
        "park": 1.0,
        "wind": 1.0,
        "temp": 0.93,
        "kTrend": 1.0,
        "bullpen": 1.0,
        "pitFatigue": 1.0,
        "convergence": 1.03
      }
    },
    {
      "pid": 804606,
      "name": "",
      "team": "PIT",
      "gameProb": 0.0283,
      "gameMatchup": "PIT vs CIN",
      "battingOrder": 1,
      "pitcherName": "Brady Singer",
      "grade": "D",
      "factors": {
        "iso": 1.0,
        "platoon": 0.96,
        "park": 1.0,
        "wind": 1.0,
        "temp": 0.93,
        "kTrend": 1.0,
        "bullpen": 1.0,
        "pitFatigue": 1.0,
        "convergence": 1.03
      }
    },
    {
      "pid": 680728,
      "name": "",
      "team": "AZ",
      "gameProb": 0.0278,
      "gameMatchup": "AZ @ TB",
      "battingOrder": 4,
      "pitcherName": "Drew Rasmussen",
      "grade": "D",
      "factors": {
        "iso": 1.0,
        "platoon": 0.96,
        "park": 1.0,
        "wind": 1.0,
        "temp": 0.93,
        "kTrend": 1.0,
        "bullpen": 1.0,
        "pitFatigue": 1.0,
        "convergence": 1.0
      }
    },
    {
      "pid": 607043,
      "name": "",
      "team": "TEX",
      "gameProb": 0.0276,
      "gameMatchup": "TEX @ TOR",
      "battingOrder": 4,
      "pitcherName": "Shane Bieber",
      "grade": "D",
      "factors": {
        "iso": 1.0,
        "platoon": 0.96,
        "park": 1.0,
        "wind": 1.0,
        "temp": 0.93,
        "kTrend": 1.0,
        "bullpen": 1.0,
        "pitFatigue": 1.0,
        "convergence": 1.03
      }
    },
    {
      "pid": 516782,
      "name": "",
      "team": "KC",
      "gameProb": 0.0276,
      "gameMatchup": "KC @ CWS",
      "battingOrder": 4,
      "pitcherName": "Anthony Kay",
      "grade": "D",
      "factors": {
        "iso": 1.0,
        "platoon": 1.15,
        "park": 1.0,
        "wind": 1.0,
        "temp": 0.93,
        "kTrend": 1.0,
        "bullpen": 1.0,
        "pitFatigue": 1.0,
        "convergence": 1.03
      }
    },
    {
      "pid": 686780,
      "name": "",
      "team": "STL",
      "gameProb": 0.0274,
      "gameMatchup": "STL vs MIA",
      "battingOrder": 9,
      "pitcherName": "Tyler Phillips",
      "grade": "D",
      "factors": {
        "iso": 1.0,
        "platoon": 0.96,
        "park": 1.0,
        "wind": 1.0,
        "temp": 0.93,
        "kTrend": 1.0,
        "bullpen": 1.0,
        "pitFatigue": 1.0,
        "convergence": 1.03
      }
    },
    {
      "pid": 691458,
      "name": "",
      "team": "STL",
      "gameProb": 0.0273,
      "gameMatchup": "STL vs MIA",
      "battingOrder": 7,
      "pitcherName": "Tyler Phillips",
      "grade": "D",
      "factors": {
        "iso": 1.0,
        "platoon": 0.96,
        "park": 1.0,
        "wind": 1.0,
        "temp": 0.93,
        "kTrend": 1.0,
        "bullpen": 1.0,
        "pitFatigue": 1.0,
        "convergence": 1.03
      }
    },
    {
      "pid": 571448,
      "name": "",
      "team": "AZ",
      "gameProb": 0.027,
      "gameMatchup": "AZ @ TB",
      "battingOrder": 7,
      "pitcherName": "Drew Rasmussen",
      "grade": "D",
      "factors": {
        "iso": 1.0,
        "platoon": 0.96,
        "park": 1.0,
        "wind": 1.0,
        "temp": 0.93,
        "kTrend": 1.0,
        "bullpen": 1.0,
        "pitFatigue": 1.0,
        "convergence": 1.03
      }
    },
    {
      "pid": 671289,
      "name": "",
      "team": "COL",
      "gameProb": 0.027,
      "gameMatchup": "COL @ MIN",
      "battingOrder": 2,
      "pitcherName": "Connor Prielipp",
      "grade": "D",
      "factors": {
        "iso": 1.0,
        "platoon": 1.15,
        "park": 1.0,
        "wind": 1.0,
        "temp": 0.93,
        "kTrend": 1.0,
        "bullpen": 1.0,
        "pitFatigue": 1.0,
        "convergence": 1.03
      }
    },
    {
      "pid": 666211,
      "name": "",
      "team": "HOU",
      "gameProb": 0.0268,
      "gameMatchup": "HOU @ DET",
      "battingOrder": 7,
      "pitcherName": "Jack Flaherty",
      "grade": "D",
      "factors": {
        "iso": 1.0,
        "platoon": 0.96,
        "park": 1.02,
        "wind": 1.0,
        "temp": 0.93,
        "kTrend": 1.0,
        "bullpen": 1.0,
        "pitFatigue": 1.0,
        "convergence": 1.03
      }
    },
    {
      "pid": 647304,
      "name": "",
      "team": "SEA",
      "gameProb": 0.0265,
      "gameMatchup": "SEA @ CLE",
      "battingOrder": 3,
      "pitcherName": "Gavin Williams",
      "grade": "D",
      "factors": {
        "iso": 1.0,
        "platoon": 0.96,
        "park": 1.0,
        "wind": 1.0,
        "temp": 0.93,
        "kTrend": 1.0,
        "bullpen": 1.0,
        "pitFatigue": 1.0,
        "convergence": 1.0
      }
    },
    {
      "pid": 545121,
      "name": "",
      "team": "AZ",
      "gameProb": 0.0265,
      "gameMatchup": "AZ @ TB",
      "battingOrder": 8,
      "pitcherName": "Drew Rasmussen",
      "grade": "D",
      "factors": {
        "iso": 1.0,
        "platoon": 0.96,
        "park": 1.0,
        "wind": 1.0,
        "temp": 0.93,
        "kTrend": 1.0,
        "bullpen": 1.0,
        "pitFatigue": 1.0,
        "convergence": 1.03
      }
    },
    {
      "pid": 663616,
      "name": "",
      "team": "MIN",
      "gameProb": 0.0263,
      "gameMatchup": "MIN vs COL",
      "battingOrder": 1,
      "pitcherName": "Ryan Feltner",
      "grade": "D",
      "factors": {
        "iso": 1.0,
        "platoon": 0.96,
        "park": 1.0,
        "wind": 1.0,
        "temp": 0.93,
        "kTrend": 1.0,
        "bullpen": 1.0,
        "pitFatigue": 1.0,
        "convergence": 1.03
      }
    },
    {
      "pid": 694378,
      "name": "",
      "team": "CWS",
      "gameProb": 0.0262,
      "gameMatchup": "CWS vs KC",
      "battingOrder": 9,
      "pitcherName": "Luinder Avila",
      "grade": "D",
      "factors": {
        "iso": 1.0,
        "platoon": 0.96,
        "park": 1.0,
        "wind": 1.0,
        "temp": 0.93,
        "kTrend": 1.0,
        "bullpen": 1.0,
        "pitFatigue": 1.0,
        "convergence": 1.0
      }
    },
    {
      "pid": 694497,
      "name": "",
      "team": "TEX",
      "gameProb": 0.0258,
      "gameMatchup": "TEX @ TOR",
      "battingOrder": 7,
      "pitcherName": "Shane Bieber",
      "grade": "D",
      "factors": {
        "iso": 1.0,
        "platoon": 0.96,
        "park": 1.0,
        "wind": 1.0,
        "temp": 0.93,
        "kTrend": 1.0,
        "bullpen": 1.0,
        "pitFatigue": 1.0,
        "convergence": 1.03
      }
    },
    {
      "pid": 701678,
      "name": "",
      "team": "DET",
      "gameProb": 0.0257,
      "gameMatchup": "DET vs HOU",
      "battingOrder": 7,
      "pitcherName": "Hunter Brown",
      "grade": "D",
      "factors": {
        "iso": 1.0,
        "platoon": 0.96,
        "park": 1.02,
        "wind": 1.0,
        "temp": 0.93,
        "kTrend": 1.0,
        "bullpen": 1.0,
        "pitFatigue": 1.0,
        "convergence": 1.03
      }
    },
    {
      "pid": 681546,
      "name": "",
      "team": "DET",
      "gameProb": 0.0257,
      "gameMatchup": "DET vs HOU",
      "battingOrder": 8,
      "pitcherName": "Hunter Brown",
      "grade": "D",
      "factors": {
        "iso": 1.0,
        "platoon": 0.96,
        "park": 1.02,
        "wind": 1.0,
        "temp": 0.93,
        "kTrend": 1.0,
        "bullpen": 1.0,
        "pitFatigue": 1.0,
        "convergence": 1.03
      }
    },
    {
      "pid": 673237,
      "name": "",
      "team": "HOU",
      "gameProb": 0.0254,
      "gameMatchup": "HOU @ DET",
      "battingOrder": 6,
      "pitcherName": "Jack Flaherty",
      "grade": "D",
      "factors": {
        "iso": 1.0,
        "platoon": 0.96,
        "park": 1.02,
        "wind": 1.0,
        "temp": 0.93,
        "kTrend": 1.0,
        "bullpen": 1.0,
        "pitFatigue": 1.0,
        "convergence": 1.03
      }
    },
    {
      "pid": 663886,
      "name": "",
      "team": "CIN",
      "gameProb": 0.0252,
      "gameMatchup": "CIN @ PIT",
      "battingOrder": 7,
      "pitcherName": "Mitch Keller",
      "grade": "D",
      "factors": {
        "iso": 1.0,
        "platoon": 0.96,
        "park": 1.0,
        "wind": 1.0,
        "temp": 0.93,
        "kTrend": 1.0,
        "bullpen": 1.0,
        "pitFatigue": 1.0,
        "convergence": 1.0
      }
    },
    {
      "pid": 665926,
      "name": "",
      "team": "TOR",
      "gameProb": 0.0251,
      "gameMatchup": "TOR vs TEX",
      "battingOrder": 9,
      "pitcherName": "Kumar Rocker",
      "grade": "D",
      "factors": {
        "iso": 1.0,
        "platoon": 0.96,
        "park": 1.0,
        "wind": 1.0,
        "temp": 0.93,
        "kTrend": 1.0,
        "bullpen": 1.0,
        "pitFatigue": 1.0,
        "convergence": 1.03
      }
    },
    {
      "pid": 695734,
      "name": "",
      "team": "WSH",
      "gameProb": 0.0246,
      "gameMatchup": "WSH @ BAL",
      "battingOrder": 6,
      "pitcherName": "Kyle Bradish",
      "grade": "D",
      "factors": {
        "iso": 1.0,
        "platoon": 0.96,
        "park": 1.0,
        "wind": 1.0,
        "temp": 0.93,
        "kTrend": 1.0,
        "bullpen": 1.0,
        "pitFatigue": 1.0,
        "convergence": 1.03
      }
    },
    {
      "pid": 690993,
      "name": "",
      "team": "DET",
      "gameProb": 0.0246,
      "gameMatchup": "DET vs HOU",
      "battingOrder": 2,
      "pitcherName": "Hunter Brown",
      "grade": "D",
      "factors": {
        "iso": 1.0,
        "platoon": 0.96,
        "park": 1.02,
        "wind": 1.0,
        "temp": 0.93,
        "kTrend": 1.0,
        "bullpen": 1.0,
        "pitFatigue": 1.0,
        "convergence": 1.0
      }
    },
    {
      "pid": 664770,
      "name": "",
      "team": "TOR",
      "gameProb": 0.0245,
      "gameMatchup": "TOR vs TEX",
      "battingOrder": 2,
      "pitcherName": "Kumar Rocker",
      "grade": "D",
      "factors": {
        "iso": 1.0,
        "platoon": 0.96,
        "park": 1.0,
        "wind": 1.0,
        "temp": 0.93,
        "kTrend": 1.0,
        "bullpen": 1.0,
        "pitFatigue": 1.0,
        "convergence": 1.0
      }
    },
    {
      "pid": 641598,
      "name": "",
      "team": "SEA",
      "gameProb": 0.0245,
      "gameMatchup": "SEA @ CLE",
      "battingOrder": 8,
      "pitcherName": "Gavin Williams",
      "grade": "D",
      "factors": {
        "iso": 1.0,
        "platoon": 0.96,
        "park": 1.0,
        "wind": 1.0,
        "temp": 0.93,
        "kTrend": 1.0,
        "bullpen": 1.0,
        "pitFatigue": 1.0,
        "convergence": 1.0
      }
    },
    {
      "pid": 701675,
      "name": "",
      "team": "STL",
      "gameProb": 0.0244,
      "gameMatchup": "STL vs MIA",
      "battingOrder": 8,
      "pitcherName": "Tyler Phillips",
      "grade": "D",
      "factors": {
        "iso": 1.0,
        "platoon": 0.96,
        "park": 1.0,
        "wind": 1.0,
        "temp": 0.93,
        "kTrend": 1.0,
        "bullpen": 1.0,
        "pitFatigue": 1.0,
        "convergence": 1.03
      }
    },
    {
      "pid": 677649,
      "name": "",
      "team": "TEX",
      "gameProb": 0.0242,
      "gameMatchup": "TEX @ TOR",
      "battingOrder": 6,
      "pitcherName": "Shane Bieber",
      "grade": "D",
      "factors": {
        "iso": 1.0,
        "platoon": 0.96,
        "park": 1.0,
        "wind": 1.0,
        "temp": 0.93,
        "kTrend": 1.0,
        "bullpen": 1.0,
        "pitFatigue": 1.0,
        "convergence": 1.03
      }
    },
    {
      "pid": 676391,
      "name": "",
      "team": "TOR",
      "gameProb": 0.0242,
      "gameMatchup": "TOR vs TEX",
      "battingOrder": 6,
      "pitcherName": "Kumar Rocker",
      "grade": "D",
      "factors": {
        "iso": 1.0,
        "platoon": 0.96,
        "park": 1.0,
        "wind": 1.0,
        "temp": 0.93,
        "kTrend": 1.0,
        "bullpen": 1.0,
        "pitFatigue": 1.0,
        "convergence": 1.03
      }
    },
    {
      "pid": 656775,
      "name": "",
      "team": "TB",
      "gameProb": 0.0242,
      "gameMatchup": "TB vs AZ",
      "battingOrder": 6,
      "pitcherName": "Merrill Kelly",
      "grade": "D",
      "factors": {
        "iso": 1.0,
        "platoon": 0.96,
        "park": 1.0,
        "wind": 1.0,
        "temp": 0.93,
        "kTrend": 1.0,
        "bullpen": 1.0,
        "pitFatigue": 1.0,
        "convergence": 1.0
      }
    },
    {
      "pid": 805808,
      "name": "",
      "team": "DET",
      "gameProb": 0.0239,
      "gameMatchup": "DET vs HOU",
      "battingOrder": 1,
      "pitcherName": "Hunter Brown",
      "grade": "D",
      "factors": {
        "iso": 1.0,
        "platoon": 0.96,
        "park": 1.02,
        "wind": 1.0,
        "temp": 0.93,
        "kTrend": 1.0,
        "bullpen": 1.0,
        "pitFatigue": 1.0,
        "convergence": 1.03
      }
    },
    {
      "pid": 663837,
      "name": "",
      "team": "DET",
      "gameProb": 0.0238,
      "gameMatchup": "DET vs HOU",
      "battingOrder": 9,
      "pitcherName": "Hunter Brown",
      "grade": "D",
      "factors": {
        "iso": 1.0,
        "platoon": 0.96,
        "park": 1.02,
        "wind": 1.0,
        "temp": 0.93,
        "kTrend": 1.0,
        "bullpen": 1.0,
        "pitFatigue": 1.0,
        "convergence": 1.03
      }
    },
    {
      "pid": 665804,
      "name": "",
      "team": "CHC",
      "gameProb": 0.0238,
      "gameMatchup": "CHC @ MIL",
      "battingOrder": 8,
      "pitcherName": "Brandon Woodruff",
      "grade": "D",
      "factors": {
        "iso": 1.0,
        "platoon": 0.96,
        "park": 1.0,
        "wind": 1.0,
        "temp": 0.93,
        "kTrend": 1.0,
        "bullpen": 1.0,
        "pitFatigue": 1.0,
        "convergence": 1.0
      }
    },
    {
      "pid": 656976,
      "name": "",
      "team": "AZ",
      "gameProb": 0.0233,
      "gameMatchup": "AZ @ TB",
      "battingOrder": 6,
      "pitcherName": "Drew Rasmussen",
      "grade": "D",
      "factors": {
        "iso": 1.0,
        "platoon": 0.96,
        "park": 1.0,
        "wind": 1.0,
        "temp": 0.93,
        "kTrend": 1.0,
        "bullpen": 1.0,
        "pitFatigue": 1.0,
        "convergence": 1.0
      }
    },
    {
      "pid": 672640,
      "name": "",
      "team": "MIA",
      "gameProb": 0.0232,
      "gameMatchup": "MIA @ STL",
      "battingOrder": 2,
      "pitcherName": "Kyle Leahy",
      "grade": "D",
      "factors": {
        "iso": 1.0,
        "platoon": 0.96,
        "park": 1.0,
        "wind": 1.0,
        "temp": 0.93,
        "kTrend": 1.0,
        "bullpen": 1.0,
        "pitFatigue": 1.0,
        "convergence": 1.03
      }
    },
    {
      "pid": 676694,
      "name": "",
      "team": "HOU",
      "gameProb": 0.0231,
      "gameMatchup": "HOU @ DET",
      "battingOrder": 8,
      "pitcherName": "Jack Flaherty",
      "grade": "D",
      "factors": {
        "iso": 1.0,
        "platoon": 0.96,
        "park": 1.02,
        "wind": 1.0,
        "temp": 0.93,
        "kTrend": 1.0,
        "bullpen": 1.0,
        "pitFatigue": 1.0,
        "convergence": 1.0
      }
    },
    {
      "pid": 666152,
      "name": "",
      "team": "MIL",
      "gameProb": 0.0228,
      "gameMatchup": "MIL vs CHC",
      "battingOrder": 9,
      "pitcherName": "Ryan Rolison",
      "grade": "D",
      "factors": {
        "iso": 1.0,
        "platoon": 1.15,
        "park": 1.0,
        "wind": 1.0,
        "temp": 0.93,
        "kTrend": 1.0,
        "bullpen": 1.0,
        "pitFatigue": 1.0,
        "convergence": 1.03
      }
    },
    {
      "pid": 687637,
      "name": "",
      "team": "BAL",
      "gameProb": 0.0225,
      "gameMatchup": "BAL vs WSH",
      "battingOrder": 6,
      "pitcherName": "Zack Littell",
      "grade": "D",
      "factors": {
        "iso": 1.0,
        "platoon": 0.96,
        "park": 1.0,
        "wind": 1.0,
        "temp": 0.93,
        "kTrend": 1.0,
        "bullpen": 1.0,
        "pitFatigue": 1.0,
        "convergence": 1.03
      }
    },
    {
      "pid": 620443,
      "name": "",
      "team": "NYM",
      "gameProb": 0.0225,
      "gameMatchup": "NYM vs PHI",
      "battingOrder": 9,
      "pitcherName": "Jes\u00fas Luzardo",
      "grade": "D",
      "factors": {
        "iso": 1.0,
        "platoon": 1.15,
        "park": 1.0,
        "wind": 1.0,
        "temp": 0.93,
        "kTrend": 1.0,
        "bullpen": 1.0,
        "pitFatigue": 1.0,
        "convergence": 1.03
      }
    },
    {
      "pid": 687859,
      "name": "",
      "team": "COL",
      "gameProb": 0.0223,
      "gameMatchup": "COL @ MIN",
      "battingOrder": 7,
      "pitcherName": "Connor Prielipp",
      "grade": "D",
      "factors": {
        "iso": 1.0,
        "platoon": 1.15,
        "park": 1.0,
        "wind": 1.0,
        "temp": 0.93,
        "kTrend": 1.0,
        "bullpen": 1.0,
        "pitFatigue": 1.0,
        "convergence": 1.06
      }
    },
    {
      "pid": 669364,
      "name": "",
      "team": "MIA",
      "gameProb": 0.0223,
      "gameMatchup": "MIA @ STL",
      "battingOrder": 4,
      "pitcherName": "Kyle Leahy",
      "grade": "D",
      "factors": {
        "iso": 1.0,
        "platoon": 0.96,
        "park": 1.0,
        "wind": 1.0,
        "temp": 0.93,
        "kTrend": 1.0,
        "bullpen": 1.0,
        "pitFatigue": 1.0,
        "convergence": 1.03
      }
    },
    {
      "pid": 688363,
      "name": "",
      "team": "MIA",
      "gameProb": 0.0223,
      "gameMatchup": "MIA @ STL",
      "battingOrder": 8,
      "pitcherName": "Kyle Leahy",
      "grade": "D",
      "factors": {
        "iso": 1.0,
        "platoon": 0.96,
        "park": 1.0,
        "wind": 1.0,
        "temp": 0.93,
        "kTrend": 1.0,
        "bullpen": 1.0,
        "pitFatigue": 1.0,
        "convergence": 1.03
      }
    },
    {
      "pid": 702284,
      "name": "",
      "team": "SEA",
      "gameProb": 0.0214,
      "gameMatchup": "SEA @ CLE",
      "battingOrder": 6,
      "pitcherName": "Gavin Williams",
      "grade": "D",
      "factors": {
        "iso": 1.0,
        "platoon": 0.96,
        "park": 1.0,
        "wind": 1.0,
        "temp": 0.93,
        "kTrend": 1.0,
        "bullpen": 1.0,
        "pitFatigue": 1.0,
        "convergence": 1.0
      }
    },
    {
      "pid": 656577,
      "name": "",
      "team": "MIN",
      "gameProb": 0.0214,
      "gameMatchup": "MIN vs COL",
      "battingOrder": 9,
      "pitcherName": "Ryan Feltner",
      "grade": "D",
      "factors": {
        "iso": 1.0,
        "platoon": 0.96,
        "park": 1.0,
        "wind": 1.0,
        "temp": 0.93,
        "kTrend": 1.0,
        "bullpen": 1.0,
        "pitFatigue": 1.0,
        "convergence": 1.0
      }
    },
    {
      "pid": 803011,
      "name": "",
      "team": "CWS",
      "gameProb": 0.021,
      "gameMatchup": "CWS vs KC",
      "battingOrder": 1,
      "pitcherName": "Luinder Avila",
      "grade": "D",
      "factors": {
        "iso": 1.0,
        "platoon": 0.96,
        "park": 1.0,
        "wind": 1.0,
        "temp": 0.93,
        "kTrend": 1.0,
        "bullpen": 1.0,
        "pitFatigue": 1.0,
        "convergence": 1.0
      }
    },
    {
      "pid": 671976,
      "name": "",
      "team": "CWS",
      "gameProb": 0.0209,
      "gameMatchup": "CWS vs KC",
      "battingOrder": 8,
      "pitcherName": "Luinder Avila",
      "grade": "D",
      "factors": {
        "iso": 1.0,
        "platoon": 0.96,
        "park": 1.0,
        "wind": 1.0,
        "temp": 0.93,
        "kTrend": 1.0,
        "bullpen": 1.0,
        "pitFatigue": 1.0,
        "convergence": 1.03
      }
    },
    {
      "pid": 686217,
      "name": "",
      "team": "MIL",
      "gameProb": 0.0209,
      "gameMatchup": "MIL vs CHC",
      "battingOrder": 7,
      "pitcherName": "Ryan Rolison",
      "grade": "D",
      "factors": {
        "iso": 1.0,
        "platoon": 1.15,
        "park": 1.0,
        "wind": 1.0,
        "temp": 0.93,
        "kTrend": 1.0,
        "bullpen": 1.0,
        "pitFatigue": 1.0,
        "convergence": 1.03
      }
    },
    {
      "pid": 678391,
      "name": "",
      "team": "WSH",
      "gameProb": 0.0208,
      "gameMatchup": "WSH @ BAL",
      "battingOrder": 8,
      "pitcherName": "Kyle Bradish",
      "grade": "D",
      "factors": {
        "iso": 1.0,
        "platoon": 0.96,
        "park": 1.0,
        "wind": 1.0,
        "temp": 0.93,
        "kTrend": 1.0,
        "bullpen": 1.0,
        "pitFatigue": 1.0,
        "convergence": 1.0
      }
    },
    {
      "pid": 694388,
      "name": "",
      "team": "HOU",
      "gameProb": 0.0204,
      "gameMatchup": "HOU @ DET",
      "battingOrder": 5,
      "pitcherName": "Jack Flaherty",
      "grade": "D",
      "factors": {
        "iso": 1.0,
        "platoon": 0.96,
        "park": 1.02,
        "wind": 1.0,
        "temp": 0.93,
        "kTrend": 1.0,
        "bullpen": 1.0,
        "pitFatigue": 1.0,
        "convergence": 1.03
      }
    },
    {
      "pid": 683146,
      "name": "",
      "team": "NYM",
      "gameProb": 0.0204,
      "gameMatchup": "NYM vs PHI",
      "battingOrder": 8,
      "pitcherName": "Jes\u00fas Luzardo",
      "grade": "D",
      "factors": {
        "iso": 1.0,
        "platoon": 1.15,
        "park": 1.0,
        "wind": 1.0,
        "temp": 0.93,
        "kTrend": 1.0,
        "bullpen": 1.0,
        "pitFatigue": 1.0,
        "convergence": 1.03
      }
    },
    {
      "pid": 686555,
      "name": "",
      "team": "KC",
      "gameProb": 0.0204,
      "gameMatchup": "KC @ CWS",
      "battingOrder": 7,
      "pitcherName": "Anthony Kay",
      "grade": "D",
      "factors": {
        "iso": 1.0,
        "platoon": 1.15,
        "park": 1.0,
        "wind": 1.0,
        "temp": 0.93,
        "kTrend": 1.0,
        "bullpen": 1.0,
        "pitFatigue": 1.0,
        "convergence": 1.03
      }
    },
    {
      "pid": 608324,
      "name": "",
      "team": "CHC",
      "gameProb": 0.0202,
      "gameMatchup": "CHC @ MIL",
      "battingOrder": 2,
      "pitcherName": "Brandon Woodruff",
      "grade": "D",
      "factors": {
        "iso": 1.0,
        "platoon": 0.96,
        "park": 1.0,
        "wind": 1.0,
        "temp": 0.93,
        "kTrend": 1.0,
        "bullpen": 1.0,
        "pitFatigue": 1.0,
        "convergence": 1.0
      }
    },
    {
      "pid": 672695,
      "name": "",
      "team": "AZ",
      "gameProb": 0.0198,
      "gameMatchup": "AZ @ TB",
      "battingOrder": 2,
      "pitcherName": "Drew Rasmussen",
      "grade": "D",
      "factors": {
        "iso": 1.0,
        "platoon": 0.96,
        "park": 1.0,
        "wind": 1.0,
        "temp": 0.93,
        "kTrend": 1.0,
        "bullpen": 1.0,
        "pitFatigue": 1.0,
        "convergence": 1.0
      }
    },
    {
      "pid": 805367,
      "name": "",
      "team": "CWS",
      "gameProb": 0.0193,
      "gameMatchup": "CWS vs KC",
      "battingOrder": 6,
      "pitcherName": "Luinder Avila",
      "grade": "D",
      "factors": {
        "iso": 1.0,
        "platoon": 0.96,
        "park": 1.0,
        "wind": 1.0,
        "temp": 0.93,
        "kTrend": 1.0,
        "bullpen": 1.0,
        "pitFatigue": 1.0,
        "convergence": 1.0
      }
    },
    {
      "pid": 677587,
      "name": "",
      "team": "CLE",
      "gameProb": 0.0188,
      "gameMatchup": "CLE vs SEA",
      "battingOrder": 6,
      "pitcherName": "Emerson Hancock",
      "grade": "D",
      "factors": {
        "iso": 1.0,
        "platoon": 0.96,
        "park": 1.0,
        "wind": 1.0,
        "temp": 0.93,
        "kTrend": 1.0,
        "bullpen": 1.0,
        "pitFatigue": 1.0,
        "convergence": 1.0
      }
    },
    {
      "pid": 621493,
      "name": "",
      "team": "BAL",
      "gameProb": 0.0187,
      "gameMatchup": "BAL vs WSH",
      "battingOrder": 1,
      "pitcherName": "Zack Littell",
      "grade": "D",
      "factors": {
        "iso": 1.0,
        "platoon": 0.96,
        "park": 1.0,
        "wind": 1.0,
        "temp": 0.93,
        "kTrend": 1.0,
        "bullpen": 1.0,
        "pitFatigue": 1.0,
        "convergence": 1.0
      }
    },
    {
      "pid": 656716,
      "name": "",
      "team": "DET",
      "gameProb": 0.0183,
      "gameMatchup": "DET vs HOU",
      "battingOrder": 6,
      "pitcherName": "Hunter Brown",
      "grade": "D",
      "factors": {
        "iso": 1.0,
        "platoon": 0.96,
        "park": 1.02,
        "wind": 1.0,
        "temp": 0.93,
        "kTrend": 1.0,
        "bullpen": 1.0,
        "pitFatigue": 1.0,
        "convergence": 1.0
      }
    },
    {
      "pid": 645302,
      "name": "",
      "team": "SEA",
      "gameProb": 0.0179,
      "gameMatchup": "SEA @ CLE",
      "battingOrder": 9,
      "pitcherName": "Gavin Williams",
      "grade": "D",
      "factors": {
        "iso": 1.0,
        "platoon": 0.96,
        "park": 1.0,
        "wind": 1.0,
        "temp": 0.93,
        "kTrend": 1.0,
        "bullpen": 1.0,
        "pitFatigue": 1.0,
        "convergence": 1.0
      }
    },
    {
      "pid": 695490,
      "name": "",
      "team": "CIN",
      "gameProb": 0.0178,
      "gameMatchup": "CIN @ PIT",
      "battingOrder": 9,
      "pitcherName": "Mitch Keller",
      "grade": "D",
      "factors": {
        "iso": 1.0,
        "platoon": 0.96,
        "park": 1.0,
        "wind": 1.0,
        "temp": 0.93,
        "kTrend": 1.0,
        "bullpen": 1.0,
        "pitFatigue": 1.0,
        "convergence": 1.0
      }
    },
    {
      "pid": 702222,
      "name": "",
      "team": "PHI",
      "gameProb": 0.0178,
      "gameMatchup": "PHI @ NYM",
      "battingOrder": 9,
      "pitcherName": "Cionel P\u00e9rez",
      "grade": "D",
      "factors": {
        "iso": 1.0,
        "platoon": 1.15,
        "park": 1.0,
        "wind": 1.0,
        "temp": 0.93,
        "kTrend": 1.0,
        "bullpen": 1.0,
        "pitFatigue": 1.0,
        "convergence": 1.03
      }
    },
    {
      "pid": 670770,
      "name": "",
      "team": "CIN",
      "gameProb": 0.0177,
      "gameMatchup": "CIN @ PIT",
      "battingOrder": 8,
      "pitcherName": "Mitch Keller",
      "grade": "D",
      "factors": {
        "iso": 1.0,
        "platoon": 0.96,
        "park": 1.0,
        "wind": 1.0,
        "temp": 0.93,
        "kTrend": 1.0,
        "bullpen": 1.0,
        "pitFatigue": 1.0,
        "convergence": 1.0
      }
    },
    {
      "pid": 666971,
      "name": "",
      "team": "AZ",
      "gameProb": 0.0176,
      "gameMatchup": "AZ @ TB",
      "battingOrder": 5,
      "pitcherName": "Drew Rasmussen",
      "grade": "D",
      "factors": {
        "iso": 1.0,
        "platoon": 0.96,
        "park": 1.0,
        "wind": 1.0,
        "temp": 0.93,
        "kTrend": 1.0,
        "bullpen": 1.0,
        "pitFatigue": 1.0,
        "convergence": 1.0
      }
    },
    {
      "pid": 665489,
      "name": "",
      "team": "TOR",
      "gameProb": 0.0175,
      "gameMatchup": "TOR vs TEX",
      "battingOrder": 3,
      "pitcherName": "Kumar Rocker",
      "grade": "D",
      "factors": {
        "iso": 1.0,
        "platoon": 0.96,
        "park": 1.0,
        "wind": 1.0,
        "temp": 0.93,
        "kTrend": 1.0,
        "bullpen": 1.0,
        "pitFatigue": 1.0,
        "convergence": 1.0
      }
    },
    {
      "pid": 805300,
      "name": "",
      "team": "MIA",
      "gameProb": 0.0175,
      "gameMatchup": "MIA @ STL",
      "battingOrder": 1,
      "pitcherName": "Kyle Leahy",
      "grade": "D",
      "factors": {
        "iso": 1.0,
        "platoon": 0.96,
        "park": 1.0,
        "wind": 1.0,
        "temp": 0.93,
        "kTrend": 1.0,
        "bullpen": 1.0,
        "pitFatigue": 1.0,
        "convergence": 1.0
      }
    },
    {
      "pid": 595978,
      "name": "",
      "team": "CLE",
      "gameProb": 0.0166,
      "gameMatchup": "CLE vs SEA",
      "battingOrder": 9,
      "pitcherName": "Emerson Hancock",
      "grade": "D",
      "factors": {
        "iso": 1.0,
        "platoon": 0.96,
        "park": 1.0,
        "wind": 1.0,
        "temp": 0.93,
        "kTrend": 1.0,
        "bullpen": 1.0,
        "pitFatigue": 1.0,
        "convergence": 1.0
      }
    },
    {
      "pid": 693304,
      "name": "",
      "team": "PIT",
      "gameProb": 0.0152,
      "gameMatchup": "PIT vs CIN",
      "battingOrder": 4,
      "pitcherName": "Brady Singer",
      "grade": "D",
      "factors": {
        "iso": 1.0,
        "platoon": 0.96,
        "park": 1.0,
        "wind": 1.0,
        "temp": 0.93,
        "kTrend": 1.0,
        "bullpen": 1.0,
        "pitFatigue": 1.0,
        "convergence": 1.0
      }
    },
    {
      "pid": 810938,
      "name": "",
      "team": "TB",
      "gameProb": 0.0151,
      "gameMatchup": "TB vs AZ",
      "battingOrder": 7,
      "pitcherName": "Merrill Kelly",
      "grade": "D",
      "factors": {
        "iso": 1.0,
        "platoon": 0.96,
        "park": 1.0,
        "wind": 1.0,
        "temp": 0.93,
        "kTrend": 1.0,
        "bullpen": 1.0,
        "pitFatigue": 1.0,
        "convergence": 1.0
      }
    },
    {
      "pid": 663968,
      "name": "",
      "team": "PIT",
      "gameProb": 0.015,
      "gameMatchup": "PIT vs CIN",
      "battingOrder": 8,
      "pitcherName": "Brady Singer",
      "grade": "D",
      "factors": {
        "iso": 1.0,
        "platoon": 0.96,
        "park": 1.0,
        "wind": 1.0,
        "temp": 0.93,
        "kTrend": 1.0,
        "bullpen": 1.0,
        "pitFatigue": 1.0,
        "convergence": 1.0
      }
    },
    {
      "pid": 663743,
      "name": "",
      "team": "TB",
      "gameProb": 0.015,
      "gameMatchup": "TB vs AZ",
      "battingOrder": 9,
      "pitcherName": "Merrill Kelly",
      "grade": "D",
      "factors": {
        "iso": 1.0,
        "platoon": 0.96,
        "park": 1.0,
        "wind": 1.0,
        "temp": 0.93,
        "kTrend": 1.0,
        "bullpen": 1.0,
        "pitFatigue": 1.0,
        "convergence": 1.0
      }
    },
    {
      "pid": 663538,
      "name": "",
      "team": "CHC",
      "gameProb": 0.015,
      "gameMatchup": "CHC @ MIL",
      "battingOrder": 6,
      "pitcherName": "Brandon Woodruff",
      "grade": "D",
      "factors": {
        "iso": 1.0,
        "platoon": 0.96,
        "park": 1.0,
        "wind": 1.0,
        "temp": 0.93,
        "kTrend": 1.0,
        "bullpen": 1.0,
        "pitFatigue": 1.0,
        "convergence": 1.0
      }
    },
    {
      "pid": 691026,
      "name": "",
      "team": "STL",
      "gameProb": 0.015,
      "gameMatchup": "STL vs MIA",
      "battingOrder": 5,
      "pitcherName": "Tyler Phillips",
      "grade": "D",
      "factors": {
        "iso": 1.0,
        "platoon": 0.96,
        "park": 1.0,
        "wind": 1.0,
        "temp": 0.93,
        "kTrend": 1.0,
        "bullpen": 1.0,
        "pitFatigue": 1.0,
        "convergence": 1.0
      }
    },
    {
      "pid": 696030,
      "name": "",
      "team": "TEX",
      "gameProb": 0.0128,
      "gameMatchup": "TEX @ TOR",
      "battingOrder": 9,
      "pitcherName": "Shane Bieber",
      "grade": "D",
      "factors": {
        "iso": 1.0,
        "platoon": 0.96,
        "park": 1.0,
        "wind": 1.0,
        "temp": 0.93,
        "kTrend": 1.0,
        "bullpen": 1.0,
        "pitFatigue": 1.0,
        "convergence": 1.0
      }
    },
    {
      "pid": 668885,
      "name": "",
      "team": "MIN",
      "gameProb": 0.0125,
      "gameMatchup": "MIN vs COL",
      "battingOrder": 8,
      "pitcherName": "Ryan Feltner",
      "grade": "D",
      "factors": {
        "iso": 1.0,
        "platoon": 0.96,
        "park": 1.0,
        "wind": 1.0,
        "temp": 0.93,
        "kTrend": 1.0,
        "bullpen": 1.0,
        "pitFatigue": 1.0,
        "convergence": 1.0
      }
    },
    {
      "pid": 807712,
      "name": "",
      "team": "MIN",
      "gameProb": 0.0119,
      "gameMatchup": "MIN vs COL",
      "battingOrder": 6,
      "pitcherName": "Ryan Feltner",
      "grade": "D",
      "factors": {
        "iso": 1.0,
        "platoon": 0.96,
        "park": 1.0,
        "wind": 1.0,
        "temp": 0.93,
        "kTrend": 1.0,
        "bullpen": 1.0,
        "pitFatigue": 1.0,
        "convergence": 1.0
      }
    },
    {
      "pid": 680757,
      "name": "",
      "team": "CLE",
      "gameProb": 0.0114,
      "gameMatchup": "CLE vs SEA",
      "battingOrder": 1,
      "pitcherName": "Emerson Hancock",
      "grade": "D",
      "factors": {
        "iso": 1.0,
        "platoon": 0.96,
        "park": 1.0,
        "wind": 1.0,
        "temp": 0.93,
        "kTrend": 1.0,
        "bullpen": 1.0,
        "pitFatigue": 1.0,
        "convergence": 1.0
      }
    },
    {
      "pid": 802415,
      "name": "",
      "team": "TB",
      "gameProb": 0.0085,
      "gameMatchup": "TB vs AZ",
      "battingOrder": 5,
      "pitcherName": "Merrill Kelly",
      "grade": "D",
      "factors": {
        "iso": 1.0,
        "platoon": 0.96,
        "park": 1.0,
        "wind": 1.0,
        "temp": 0.93,
        "kTrend": 1.0,
        "bullpen": 1.0,
        "pitFatigue": 1.0,
        "convergence": 1.0
      }
    },
    {
      "pid": 670764,
      "name": "",
      "team": "TB",
      "gameProb": 0.0076,
      "gameMatchup": "TB vs AZ",
      "battingOrder": 8,
      "pitcherName": "Merrill Kelly",
      "grade": "D",
      "factors": {
        "iso": 1.0,
        "platoon": 0.96,
        "park": 1.0,
        "wind": 1.0,
        "temp": 0.93,
        "kTrend": 1.0,
        "bullpen": 1.0,
        "pitFatigue": 1.0,
        "convergence": 1.0
      }
    }
  ]
}