{
  "calibrationBuckets": [
    {
      "lo": 0.5,
      "hi": 0.55,
      "total": 645,
      "hits": 596,
      "sumExpected": 325.80199999999985
    },
    {
      "lo": 0.55,
      "hi": 0.6,
      "total": 400,
      "hits": 258,
      "sumExpected": 232.12400000000045
    },
    {
      "lo": 0.6,
      "hi": 0.65,
      "total": 445,
      "hits": 275,
      "sumExpected": 276.6943999999999
    },
    {
      "lo": 0.65,
      "hi": 0.7,
      "total": 248,
      "hits": 170,
      "sumExpected": 166.5065
    },
    {
      "lo": 0.7,
      "hi": 0.75,
      "total": 188,
      "hits": 157,
      "sumExpected": 136.82839999999996
    },
    {
      "lo": 0.75,
      "hi": 0.8,
      "total": 197,
      "hits": 141,
      "sumExpected": 152.08940000000013
    },
    {
      "lo": 0.8,
      "hi": 0.9,
      "total": 16,
      "hits": 12,
      "sumExpected": 12.930399999999999
    },
    {
      "lo": 0.9,
      "hi": 1.01,
      "total": 0,
      "hits": 0,
      "sumExpected": 0.0
    }
  ],
  "firstSetCalibrationBuckets": [
    {
      "lo": 0.5,
      "hi": 0.55,
      "total": 817,
      "hits": 226,
      "sumExpected": 415.0503999999995
    },
    {
      "lo": 0.55,
      "hi": 0.6,
      "total": 598,
      "hits": 364,
      "sumExpected": 344.1826000000001
    },
    {
      "lo": 0.6,
      "hi": 0.65,
      "total": 325,
      "hits": 220,
      "sumExpected": 203.7877000000001
    },
    {
      "lo": 0.65,
      "hi": 0.7,
      "total": 125,
      "hits": 98,
      "sumExpected": 83.4029
    },
    {
      "lo": 0.7,
      "hi": 0.75,
      "total": 183,
      "hits": 147,
      "sumExpected": 133.26579999999993
    },
    {
      "lo": 0.75,
      "hi": 0.8,
      "total": 91,
      "hits": 62,
      "sumExpected": 69.4086
    },
    {
      "lo": 0.8,
      "hi": 0.9,
      "total": 0,
      "hits": 0,
      "sumExpected": 0.0
    },
    {
      "lo": 0.9,
      "hi": 1.01,
      "total": 0,
      "hits": 0,
      "sumExpected": 0.0
    }
  ],
  "accuracySummary": {
    "hits": 1609,
    "total": 2139
  },
  "firstSetAccuracySummary": {
    "hits": 1117,
    "total": 2139
  },
  "lastUpdated": "2026-07-17"
}